{
  "video_id": "7579879830137605376",
  "url": "https://www.douyin.com/video/7579879830137605376",
  "author": "大巾探",
  "author_id": "985624653867032",
  "title": "现在这小姑娘太厉害了，能做出这么好的成绩！",
  "analyzed_at": "2026-04-25T01:23:00.000Z",
  "quality": "accessible",
  "main_content": "卖中式披萨卖出了不可思议的成绩，这个小姑娘跟着干了8年时间卖了2000万个中式披萨，你没听错是2000万个。现在他们有直营店、合作店还有最新开发的电中电模式。博主决定以真实视角去采访一下这个小姑娘，看看她到底是怎么做的。博主问：你们真卖了2000万个中式披萨？她说：还能有假，就算我没有卖那么多，但这可是真的。她干了八年，之前八年前就开了一个面馆，结果面里的这个中式披萨比面卖的还要好，就单独出来做这个中式披萨了。博主说：咱们去参观一下电中电模式吧。她说：可以带你去看一下，因为我们现在这个模式已经很稳了。博主来到一个典型的餐饮门店，看到跟他们合作的一个烤披萨的烤箱。博主说：你不要告诉我电中电就是一个烤箱？她说：但是你别看他只是一个普通的烤箱，他都会烤。合作方大哥正在做，博主说绝对要尝一下。博主问：这个是什么味道？她说：这个是芝士的。博主说：这个芝士培根是九块钱？她说：芝士烤肠是八块钱，来三个带回家。博主说：芝士烤肠几块？还有肉的呢？她说：你等会儿先尝一下这个鲜肉的，这个是我们的招牌。博主说：芝士鲜肉的这个很香，这个绝对比那个好，吃过的绝对会来复购。一个是做的肠的外酥里嫩软，香气漂亮，是八个钱的，真的没错。芝士的冒油看到没有，这个比在别处的好。博主问：你是怎么跟这三家合作的？她说：借它的门店、借它的员工、借它的流量，做咱们自己的生意。博主说：那你不就借鸡生蛋了吗？她说：对啊就是这样。博主问：你能把这个做到这一步吗？她说：小瞧我了是吧。博主问：你这个电中电模式做了多久？她说：大半年。博主问：中式披萨做了多久？她说：8年。博主说：那我是不是可以跟你学，我去拖这个机器然后咱们俩直接分开干？她说：你会抓住重点。现在马上有一家下午刚谈的合作正在装设备，可以去看，那个店比刚才那个店大很多。另一个合作方说：我跟丽娜合作这个电中店模式，现在也没合作太久，一共30多家，每天可以铺一两家。博主问：是因为信任你这个人来的吗？她说：有很多人就是因为丽娜才过来，也有很多像他这样的合作方主动来推，因为确实有很多成功案例，大家都不傻不可能干赔本的买卖。合作方说：吃了她那个饼之后觉得如果开在家门口肯定老顾客会来买。博主问：每家店都这样吗？她说是的。博主问：机器成本高吗？她说：还好，因为我们都是无限量公益，只要能卖出去有多少送多少。博主问：这么多吗？她说是的。博主说你跟着赶紧了，这两年多现在规矩帮你干。博主说其实还是用互联网思维去做这个事情。关键成功因素：产品好吃是根本，合作模式轻资产，设备免费投放降低门槛，通过成功案例吸引更多合作方主动加入。设备是无限量公益投放，只要能卖出去有多少送多少。博主评价：用互联网思维做餐饮，产品非常有自信，做了直营店、餐车还有电中店，全是小姑娘一个人在操持，欢迎大家来品尝。产品好吃是根本，合作模式轻资产，设备免费投放降低门槛，通过成功案例吸引更多合作方主动加入。很多人因为信任她才过来合作，也有很多像他这样的合作方主动来推，因为确实有很多成功案例，大家都不傻不可能干赔本的买卖。合作方说吃了她那个饼之后觉得如果开在家门口肯定老顾客会来买。博主问每家店都这样吗？她说是的。博主问机器成本高吗？她说还好，因为我们都是无限量公益，只要能卖出去有多少送多少。博主问这么多吗？她说是的。博主说你跟着赶紧了，这两年多现在规矩帮你干。博主说其实还是用互联网思维去做这个事情。用互联网思维做餐饮，产品非常有自信，做了直营店、餐车还有电中店，全是小姑娘一个人在操持，欢迎大家来品尝。"
}