{
  "video_id": "7562862735701167412",
  "url": "https://www.douyin.com/video/7562862735701167412",
  "author": "在野-商业课",
  "author_id": "94651422906",
  "title": "从老土国货到年入260亿，波司登凭什么逆袭成国民潮牌？ #每天跟我涨知识#商业案例#商业模式#商业思维#波司登",
  "analyzed_at": "2026-04-25T14:00:00.000Z",
  "quality": "accessible",
  "main_content": "博主分享了波司登从老牌国货变成潮流品牌的转型案例。提到波司登你第一反应是什么是不是先想到老牌羽绒服，但现在再看波司登是不是觉得都变时尚了甚至带点国际化的范。不光是形象大变身业绩更是肉眼可见的猛，他刚发布23-25财年报告里集团营收259亿净利润35.1亿，要知道十年前他的净利润才两三亿这一翻就是十多倍。最难得的是他没靠新品牌没靠年轻化的品牌就靠波司登本身。波司登不算新玩家1976年就成立了2007年还在港股上了市，2017年左右他已经是国民级的羽绒服品牌在专门做羽绒服的企业里市场份额占了足足40%。但也正是这时候他遇上了大瓶颈内部觉得只卖羽绒服天花板太低得扩品类才能长，当时波司登也是想过破局跟着行业常见思路走做了调研定方案最后决定做多元化卖女装童装居家用品前前后后投了几十亿，结果消费者根本不买账大家心里波司登等于羽绒服的印象太根深蒂固了你突然卖女装没人认市场也不认可这些新业务不仅没赚钱反而成了拖后腿的负资产。这困境其实很多老品牌都遇过想突破却找错了方向。后来波司登及时踩了刹车重新复盘发现两个关键问题：一是消费者认知改不了，二是自己把羽绒服市场看小了之前算的40%份额只是局现在专业羽绒服品牌里当大家买羽绒服还会选优衣库耐克甚至北面迪桑特这些户外品牌把这些都算进去波司登的市场份额其实只有百分之六这一下增长空间瞬间清晰了。于是波司登果断定了战略不搞多元化就聚焦羽绒服把它当成唯一主战场。战略定了更难的还在后头怎么摆脱老气标签让年轻人愿意买？破局点是登上国际舞台刷新时尚形象，波司登是第一个受纽约时装周官方邀约独立走秀的中国羽绒服品牌后来还陆续登上米兰时装周伦敦时装周把羽绒服设计得又保暖又有型一下就跟传统老国货的形象划清了界限。产品也得跟上以前波司登做产品就是看去年哪个卖得好改改细节当新款跟帮别的品牌代工没什么新意，后来它彻底改了产品逻辑从卖单品变成推系列针对不同需求做细分：户外的滑雪服系列、日常的极寒系列、还有专业适合北方的高登户外系列能应对登山滑雪这些场景。这招特别有效营收就从六十多亿赚到快九十亿。后来波司登更聪明了直接按场景来布局产品：户外场景有专业款、商务场景有利落的通勤款、休闲场景有百搭的基础款每个场景里还分不同价格段不管你是学生还是上班族都能找到合适的。最聪明的是他卖防晒衣你可能会问羽绒服品牌卖什么防晒衣这里面藏着两个小心思：第一防晒衣也是功能服饰跟羽绒服的面料优势能承接大家认知里不违和；第二解决了羽绒服单季卖货的痛点以前夏天门店要么转租要么关门员工留不住好员工也不愿意来现在夏天卖防晒衣门店能正常运营还能靠防晒衣吸引年轻人进店顺便带动秋冬的羽绒服销售一举两得。波司登甚至推出了上万的高端系列把羽绒服做成了高端单品在羽绒服领域的护城河是越来越深。其实他的成功不是靠大运气而是每年都有明确的目标今年解决形象问题明年优化产品后年拓展场景一步步把品牌形象产品矩阵都打磨到位。波司登的逆袭没什么秘诀就是抓住了两个核心：一是不跟消费者认知较劲尊重自己最擅长的事；二是不偷懒从形象到产品每一步都踩在用户需求上。从老土国货到年入261亿其实是给所有老品牌打了个样只要找对风向深耕下去就能越活越年轻。"
}