{
  "video_id": "7611789544081460495",
  "url": "https://www.douyin.com/video/7611789544081460495",
  "author": "洪树",
  "author_id": "1358616830158588",
  "analyzed_at": "2026-04-20T06:00:00.000Z",
  "quality": "accessible",
  "topic": "识别工作能力强的人的三个维度：表达、同理心、有效动作",
  "main_content": "怎么让人看一眼就觉得你的工作能力很强？能力强的人身上都有一种味道，它不是靠鼻子去闻，因为它是一种非常干净利落的味道。大部分普通人都是高内耗体，不管走到哪都会把自己的情绪和混乱带到哪；而能力强的人都是低内耗体，身上没有多余的东西，把它放到任何一个环境，它都可以把复杂的事情变得简单，把混乱的秩序变得有序。那我们怎么去识别这种人呢？第一点，听他说的话有没有废话，听完了以后你会不会听不懂。因为大部分人聊天或者是汇报工作的时候，他喜欢先上来说背景、说自己干了什么、说自己遇到什么困难，然后讲了一大堆没有重点，你也不知道他的目的是什么。能力强的人他的表达习惯是反过来的，他们一般是先说结论、先讲诉求或者是先提问题，只有当你想展开讨论的时候他才会再去补充一些必要的信息。为什么呢？因为他很重视时间，这不仅仅是尊重自己的时间，也是尊重对方的时间，所以他讲话的时候不喜欢绕弯子。而且还有一点，在你们整个交流的过程中，他的情绪基本是处于稳定状态。但普通人就不然，很多人遇到一点点急事烂事，他的嗓门就会越来越大，他的语速就会越来越快，哪怕你隔他两三米远，你都能从他身上闻到那种焦虑的味道。所以高手他通常都是反人性的，事越大他说话的声音反而越沉，他说话的速度反而越慢。倒不是说他不着急，而是他知道在这个时候去发泄情绪是最没有用的事情，所以他必须成为那个能够给所有人降温的冰块。这种遇事冷静、表达清晰有逻辑的状态，就是能力强的人的典型特征。第二个方面就是你要看他有没有很强的同理心，因为同理心是智商和情商兼备的一种体现。如果一个人只有智商但没有情商，那他就是人机，他虽然可以帮你解决问题，但是你会很难跟他共事；如果一个人只有情商但能力不行，也不能委以重任，因为他会很容易感情用事。只有那种同理心很强的人才是真正的高手，因为他会一边对自己的个人目标非常执着，同时他能够跳出自我，站在客户的视角、站在老板的视角、甚至是站在敌人的视角去思考问题。在必要的时候他可以见人说人话、见鬼说鬼话，这并不是说他很虚伪，而是他为了探清底线，在不翻脸的情况下还能够与各方去达成共识。你会发现他完全是站在上帝视角往下看，然后不断地为团队、为他个人去争取利益。你要是有机会跟这种人共事，你又会发现你跟他沟通起来会非常舒服，因为他知道你需要什么，甚至在很多时候有些重要的事情连你自己都忘了，他都会帮你去考虑。这就是强大的同理心。第三点就是你要看他做事情的时候有没有多余的动作。我之前还在上班的时候，有一天我刚刚吃完饭正准备上楼，我在楼梯间里面碰到我的老板，他准备下班回家了。我当时非常不理解，说你每天有那么多事情、那么多会、那么重的目标，为什么你看起来那么轻松？他跟我说，如果你很忙是因为你没有判断力；如果你的事情多到做不完、你很焦虑，是因为你多余的动作太多了。那个时候我是初入职场，其实我并不理解他在说什么，但当时我就是那种不管做什么都是不留余力的人。随着我在职场上待的时间越来越久，我才发现其实我们身边都有这种人，就是那种每天忙里忙外，不管大事还是小事他都接，不管重要还是不重要的活他都干，但最后只要涉及到晋升或者是评级，你就会发现他根本没有什么拿得出手的业绩。为什么每天很忙？恰恰是因为他不知道什么事情是最重要的，他什么都做，他就一定什么都做不好。不管是工作也好还是创业也好，它并不是在考试，你并不需要把每道题都做对，你甚至都不需要把这张试卷给做完。那种胡子眉毛一把抓的人，每天看起来很充实，但这反而是一种没有看清大局的愚蠢和无知。真正的高手他有一种穿透复杂事物的能力，他能够在一团乱麻中间找到那根关键的线头，然后剩下的问题就迎刃而解了。因为他很清楚，对于一个业务来说，90%的产出来自于那个10%的有效动作。你首先需要把那个10%的有效动作给揪出来，然后用90%的精力和时间去重复这个动作。所以高手做事情从来都不是靠蛮力，而是靠阅历，要么就不出手，一出手就是胜负手。所以你发现没有，这种能力很强的人他都是低内耗体，没有多余的废话、没有多余的情绪、也没有多余的动作。他不会夸夸其谈，他严厉只有对专业的敬畏、对赢的渴望，这才是真大佬。"
}