{
  "blogger_name": "沉默的羊男",
  "blogger_id": "706305833834045",
  "sec_uid": "MS4wLjABAAAAe1cy_3g38MVXDZu2GQq5S9i57N2NFxmerfiTK1BIJYo",
  "blogger_url": "https://www.douyin.com/user/MS4wLjABAAAAe1cy_3g38MVXDZu2GQq5S9i57N2NFxmerfiTK1BIJYo",
  "avatar_url": null,
  "follower_count": 3776,
  "following_count": 0,
  "likes_count": 0,
  "video_count": 0,
  "douyin_id": null,
  "ip_location": null,
  "signature": null,
  "score": 85,
  "source_keyword": "自媒体变现",
  "discovered_at": "2026-04-22T19:20:08.790Z",
  "last_fetch_time": "2026-04-25T08:45:01.701Z",
  "collected_video_count": 5,
  "category": "自媒体重启与低成本创业",
  "summary": "自媒体重启型博主，侧重离职后做自媒体的反思和低成本起步。风格：真实记录、反思总结",
  "total_videos": 5,
  "high_quality_count": 4,
  "low_quality_count": 0,
  "inaccessible_count": 0,
  "high_quality_ratio": 0.8,
  "low_quality_ratio": 0,
  "project_related_count": null,
  "project_names": null,
  "last_analyzed_at": "2026-04-25T09:32:00.000Z",
  "relevance_score": 55,
  "comment_analysis": null,
  "comment_data": null,
  "videos": [
    {
      "url": "https://www.douyin.com/video/7612195910260666041",
      "aweme_id": "7612195910260666041",
      "create_time": "2026-03-01T08:07:55.000Z",
      "collect_time": "2026-04-23T05:02:03.770Z",
      "status": "pending",
      "title": "强者从不抱怨环境❗20㎡出租屋做自媒体经验 打造一个合适的空间拍视频对博主来说是很重要的一件事,主要做好2点:调性和效率! 1.调性 学会打光,置景只是基础打光才是提升最大的 2.……版本过低，升级后可展示全部信息",
      "is_pinned": false,
      "play_count": 510,
      "play_count_display": "510",
      "duration": 220,
      "digg_count": 510,
      "comment_count": 9,
      "share_count": 6,
      "collect_count": 43,
      "isIncomplete": false
    },
    {
      "url": "https://www.douyin.com/video/7598530025483681265",
      "aweme_id": "7598530025483681265",
      "create_time": "2026-01-23T12:17:19.000Z",
      "collect_time": "2026-04-23T17:55:56.098Z",
      "status": "pending",
      "title": "年终总结：离职博主失败，但勇闯自媒体成功 这一年真是低开高走了，年初做自媒体失败回到职场，我开始反思总结自己过去的决策，痛定思痛后反而更清晰。 1.我要有一个可持续输出的内容方向 ……版本过低，升级后可展示全部信息",
      "is_pinned": false,
      "play_count": 6,
      "play_count_display": "6",
      "duration": 204,
      "digg_count": 6,
      "comment_count": 0,
      "share_count": 0,
      "collect_count": 3,
      "isIncomplete": false
    },
    {
      "url": "https://www.douyin.com/video/7583244500203982129",
      "aweme_id": "7583244500203982129",
      "create_time": "2025-12-13T07:42:06.000Z",
      "collect_time": "2026-04-24T08:22:28.755Z",
      "status": "pending",
      "title": "别纠结赛道了，3分钟带你做出一条好视频！ #拍摄教程技巧 #拍摄技巧 #自媒体 #自媒体干货 #干货分享",
      "is_pinned": false,
      "play_count": 54,
      "play_count_display": "54",
      "duration": 224,
      "digg_count": 54,
      "comment_count": 5,
      "share_count": 1,
      "collect_count": 9,
      "isIncomplete": false
    },
    {
      "url": "https://www.douyin.com/video/7582623339660905787",
      "aweme_id": "7582623339660905787",
      "create_time": "2025-12-11T15:31:45.000Z",
      "collect_time": "2026-04-25T01:40:30.901Z",
      "status": "pending",
      "title": "我们杀死了多个自己，才长成一个普通大人 18岁我想当个艺术家，但我发现艺术梦，就像上海的梧桐区别墅出生没有一辈子也不会有。 22岁我想当个知名摄影师，但是我发现有时候不是你不够好而……版本过低，升级后可展示全部信息",
      "is_pinned": false,
      "play_count": 0,
      "play_count_display": "0",
      "duration": 228,
      "digg_count": 89,
      "comment_count": 13,
      "share_count": 8,
      "collect_count": 14,
      "isIncomplete": false
    },
    {
      "aweme_id": "7582831850948594993",
      "url": "https://www.douyin.com/video/7582831850948594993",
      "author": "沉默的羊男",
      "title": "拼尽全力写给生活的情书——热爱不要停！！ #青年创作者成长计划 #vlog #在拍一种很新的vlog",
      "status": "pending",
      "is_pinned": false,
      "play_count": 0,
      "play_count_display": "0",
      "duration": 193,
      "digg_count": 50,
      "comment_count": 2,
      "share_count": 3,
      "collect_count": 11,
      "create_time": "2025-12-12T05:00:35.000Z",
      "collect_time": "2026-04-25T08:45:01.701Z"
    }
  ],
  "keywords_history": null,
  "categories_history": null
}