{"nodes": [{"id": "d_opencli_src_utils_ts", "label": "utils.ts", "file_type": "code", "source_file": "D:\\opencli\\src\\utils.ts", "source_location": "L1"}, {"id": "utils_isrecord", "label": "isRecord()", "file_type": "code", "source_file": "D:\\opencli\\src\\utils.ts", "source_location": "L10"}, {"id": "utils_mapconcurrent", "label": "mapConcurrent()", "file_type": "code", "source_file": "D:\\opencli\\src\\utils.ts", "source_location": "L15"}, {"id": "utils_sleep", "label": "sleep()", "file_type": "code", "source_file": "D:\\opencli\\src\\utils.ts", "source_location": "L36"}, {"id": "utils_savebase64tofile", "label": "saveBase64ToFile()", "file_type": "code", "source_file": "D:\\opencli\\src\\utils.ts", "source_location": "L41"}, {"id": "utils_createmarkdownconverter", "label": "createMarkdownConverter()", "file_type": "code", "source_file": "D:\\opencli\\src\\utils.ts", "source_location": "L47"}, {"id": "utils_htmltomarkdown", "label": "htmlToMarkdown()", "file_type": "code", "source_file": "D:\\opencli\\src\\utils.ts", "source_location": "L63"}], "edges": [{"source": "d_opencli_src_utils_ts", "target": "node_fs", "relation": "imports_from", "confidence": "EXTRACTED", "source_file": "D:\\opencli\\src\\utils.ts", "source_location": "L5", "weight": 1.0}, {"source": "d_opencli_src_utils_ts", "target": "node_path", "relation": "imports_from", "confidence": "EXTRACTED", "source_file": "D:\\opencli\\src\\utils.ts", "source_location": "L6", "weight": 1.0}, {"source": "d_opencli_src_utils_ts", "target": "turndown", "relation": "imports_from", "confidence": "EXTRACTED", "source_file": "D:\\opencli\\src\\utils.ts", "source_location": "L7", "weight": 1.0}, {"source": "d_opencli_src_utils_ts", "target": "utils_isrecord", "relation": "contains", "confidence": "EXTRACTED", "source_file": "D:\\opencli\\src\\utils.ts", "source_location": "L10", "weight": 1.0}, {"source": "d_opencli_src_utils_ts", "target": "utils_mapconcurrent", "relation": "contains", "confidence": "EXTRACTED", "source_file": "D:\\opencli\\src\\utils.ts", "source_location": "L15", "weight": 1.0}, {"source": "d_opencli_src_utils_ts", "target": "utils_sleep", "relation": "contains", "confidence": "EXTRACTED", "source_file": "D:\\opencli\\src\\utils.ts", "source_location": "L36", "weight": 1.0}, {"source": "d_opencli_src_utils_ts", "target": "utils_savebase64tofile", "relation": "contains", "confidence": "EXTRACTED", "source_file": "D:\\opencli\\src\\utils.ts", "source_location": "L41", "weight": 1.0}, {"source": "d_opencli_src_utils_ts", "target": "utils_createmarkdownconverter", "relation": "contains", "confidence": "EXTRACTED", "source_file": "D:\\opencli\\src\\utils.ts", "source_location": "L47", "weight": 1.0}, {"source": "d_opencli_src_utils_ts", "target": "utils_htmltomarkdown", "relation": "contains", "confidence": "EXTRACTED", "source_file": "D:\\opencli\\src\\utils.ts", "source_location": "L63", "weight": 1.0}, {"source": "utils_htmltomarkdown", "target": "utils_createmarkdownconverter", "relation": "calls", "confidence": "EXTRACTED", "source_file": "D:\\opencli\\src\\utils.ts", "source_location": "L64", "weight": 1.0}], "raw_calls": [{"caller_nid": "utils_isrecord", "callee": "isArray", "source_file": "D:\\opencli\\src\\utils.ts", "source_location": "L11"}, {"caller_nid": "utils_mapconcurrent", "callee": "from", "source_file": "D:\\opencli\\src\\utils.ts", "source_location": "L30"}, {"caller_nid": "utils_mapconcurrent", "callee": "min", "source_file": "D:\\opencli\\src\\utils.ts", "source_location": "L30"}, {"caller_nid": "utils_mapconcurrent", "callee": "all", "source_file": "D:\\opencli\\src\\utils.ts", "source_location": "L31"}, {"caller_nid": "utils_savebase64tofile", "callee": "dirname", "source_file": "D:\\opencli\\src\\utils.ts", "source_location": "L42"}, {"caller_nid": "utils_savebase64tofile", "callee": "mkdir", "source_file": "D:\\opencli\\src\\utils.ts", "source_location": "L43"}, {"caller_nid": "utils_savebase64tofile", "callee": "writeFile", "source_file": "D:\\opencli\\src\\utils.ts", "source_location": "L44"}, {"caller_nid": "utils_savebase64tofile", "callee": "from", "source_file": "D:\\opencli\\src\\utils.ts", "source_location": "L44"}, {"caller_nid": "utils_createmarkdownconverter", "callee": "addRule", "source_file": "D:\\opencli\\src\\utils.ts", "source_location": "L54"}, {"caller_nid": "utils_createmarkdownconverter", "callee": "configure", "source_file": "D:\\opencli\\src\\utils.ts", "source_location": "L59"}, {"caller_nid": "utils_htmltomarkdown", "callee": "trim", "source_file": "D:\\opencli\\src\\utils.ts", "source_location": "L64"}, {"caller_nid": "utils_htmltomarkdown", "callee": "replace", "source_file": "D:\\opencli\\src\\utils.ts", "source_location": "L64"}, {"caller_nid": "utils_htmltomarkdown", "callee": "replace", "source_file": "D:\\opencli\\src\\utils.ts", "source_location": "L64"}, {"caller_nid": "utils_htmltomarkdown", "callee": "replace", "source_file": "D:\\opencli\\src\\utils.ts", "source_location": "L64"}, {"caller_nid": "utils_htmltomarkdown", "callee": "turndown", "source_file": "D:\\opencli\\src\\utils.ts", "source_location": "L64"}]}