{"nodes": [{"id": "d_opencli_extension_src_background_ts", "label": "background.ts", "file_type": "code", "source_file": "D:\\opencli\\extension\\src\\background.ts", "source_location": "L1"}, {"id": "background_forwardlog", "label": "forwardLog()", "file_type": "code", "source_file": "D:\\opencli\\extension\\src\\background.ts", "source_location": "L26"}, {"id": "background_connect", "label": "connect()", "file_type": "code", "source_file": "D:\\opencli\\extension\\src\\background.ts", "source_location": "L47"}, {"id": "background_schedulereconnect", "label": "scheduleReconnect()", "file_type": "code", "source_file": "D:\\opencli\\extension\\src\\background.ts", "source_location": "L107"}, {"id": "background_getidletimeout", "label": "getIdleTimeout()", "file_type": "code", "source_file": "D:\\opencli\\extension\\src\\background.ts", "source_location": "L140"}, {"id": "background_getworkspacekey", "label": "getWorkspaceKey()", "file_type": "code", "source_file": "D:\\opencli\\extension\\src\\background.ts", "source_location": "L151"}, {"id": "background_resetwindowidletimer", "label": "resetWindowIdleTimer()", "file_type": "code", "source_file": "D:\\opencli\\extension\\src\\background.ts", "source_location": "L155"}, {"id": "background_getautomationwindow", "label": "getAutomationWindow()", "file_type": "code", "source_file": "D:\\opencli\\extension\\src\\background.ts", "source_location": "L185"}, {"id": "background_initialize", "label": "initialize()", "file_type": "code", "source_file": "D:\\opencli\\extension\\src\\background.ts", "source_location": "L265"}, {"id": "background_handlecommand", "label": "handleCommand()", "file_type": "code", "source_file": "D:\\opencli\\extension\\src\\background.ts", "source_location": "L300"}, {"id": "background_isdebuggableurl", "label": "isDebuggableUrl()", "file_type": "code", "source_file": "D:\\opencli\\extension\\src\\background.ts", "source_location": "L355"}, {"id": "background_issafenavigationurl", "label": "isSafeNavigationUrl()", "file_type": "code", "source_file": "D:\\opencli\\extension\\src\\background.ts", "source_location": "L361"}, {"id": "background_normalizeurlforcomparison", "label": "normalizeUrlForComparison()", "file_type": "code", "source_file": "D:\\opencli\\extension\\src\\background.ts", "source_location": "L366"}, {"id": "background_istargeturl", "label": "isTargetUrl()", "file_type": "code", "source_file": "D:\\opencli\\extension\\src\\background.ts", "source_location": "L380"}, {"id": "background_matchesdomain", "label": "matchesDomain()", "file_type": "code", "source_file": "D:\\opencli\\extension\\src\\background.ts", "source_location": "L384"}, {"id": "background_matchesbindcriteria", "label": "matchesBindCriteria()", "file_type": "code", "source_file": "D:\\opencli\\extension\\src\\background.ts", "source_location": "L394"}, {"id": "background_setworkspacesession", "label": "setWorkspaceSession()", "file_type": "code", "source_file": "D:\\opencli\\extension\\src\\background.ts", "source_location": "L408"}, {"id": "background_resolvecommandtabid", "label": "resolveCommandTabId()", "file_type": "code", "source_file": "D:\\opencli\\extension\\src\\background.ts", "source_location": "L422"}, {"id": "background_resolvetab", "label": "resolveTab()", "file_type": "code", "source_file": "D:\\opencli\\extension\\src\\background.ts", "source_location": "L433"}, {"id": "background_pagescopedresult", "label": "pageScopedResult()", "file_type": "code", "source_file": "D:\\opencli\\extension\\src\\background.ts", "source_location": "L503"}, {"id": "background_resolvetabid", "label": "resolveTabId()", "file_type": "code", "source_file": "D:\\opencli\\extension\\src\\background.ts", "source_location": "L509"}, {"id": "background_listautomationtabs", "label": "listAutomationTabs()", "file_type": "code", "source_file": "D:\\opencli\\extension\\src\\background.ts", "source_location": "L514"}, {"id": "background_listautomationwebtabs", "label": "listAutomationWebTabs()", "file_type": "code", "source_file": "D:\\opencli\\extension\\src\\background.ts", "source_location": "L533"}, {"id": "background_handleexec", "label": "handleExec()", "file_type": "code", "source_file": "D:\\opencli\\extension\\src\\background.ts", "source_location": "L538"}, {"id": "background_handlenavigate", "label": "handleNavigate()", "file_type": "code", "source_file": "D:\\opencli\\extension\\src\\background.ts", "source_location": "L551"}, {"id": "background_handletabs", "label": "handleTabs()", "file_type": "code", "source_file": "D:\\opencli\\extension\\src\\background.ts", "source_location": "L651"}, {"id": "background_handlecookies", "label": "handleCookies()", "file_type": "code", "source_file": "D:\\opencli\\extension\\src\\background.ts", "source_location": "L717"}, {"id": "background_handlescreenshot", "label": "handleScreenshot()", "file_type": "code", "source_file": "D:\\opencli\\extension\\src\\background.ts", "source_location": "L737"}, {"id": "background_handlecdp", "label": "handleCdp()", "file_type": "code", "source_file": "D:\\opencli\\extension\\src\\background.ts", "source_location": "L776"}, {"id": "background_handleclosewindow", "label": "handleCloseWindow()", "file_type": "code", "source_file": "D:\\opencli\\extension\\src\\background.ts", "source_location": "L797"}, {"id": "background_handlesetfileinput", "label": "handleSetFileInput()", "file_type": "code", "source_file": "D:\\opencli\\extension\\src\\background.ts", "source_location": "L814"}, {"id": "background_handleinserttext", "label": "handleInsertText()", "file_type": "code", "source_file": "D:\\opencli\\extension\\src\\background.ts", "source_location": "L828"}, {"id": "background_handlenetworkcapturestart", "label": "handleNetworkCaptureStart()", "file_type": "code", "source_file": "D:\\opencli\\extension\\src\\background.ts", "source_location": "L842"}, {"id": "background_handlenetworkcaptureread", "label": "handleNetworkCaptureRead()", "file_type": "code", "source_file": "D:\\opencli\\extension\\src\\background.ts", "source_location": "L853"}, {"id": "background_handlesessions", "label": "handleSessions()", "file_type": "code", "source_file": "D:\\opencli\\extension\\src\\background.ts", "source_location": "L864"}, {"id": "background_handlebindcurrent", "label": "handleBindCurrent()", "file_type": "code", "source_file": "D:\\opencli\\extension\\src\\background.ts", "source_location": "L875"}], "edges": [{"source": "d_opencli_extension_src_background_ts", "target": "d_opencli_extension_src_protocol", "relation": "imports_from", "confidence": "EXTRACTED", "source_file": "D:\\opencli\\extension\\src\\background.ts", "source_location": "L10", "weight": 1.0}, {"source": "d_opencli_extension_src_background_ts", "target": "d_opencli_extension_src_protocol", "relation": "imports_from", "confidence": "EXTRACTED", "source_file": "D:\\opencli\\extension\\src\\background.ts", "source_location": "L11", "weight": 1.0}, {"source": "d_opencli_extension_src_background_ts", "target": "d_opencli_extension_src_cdp", "relation": "imports_from", "confidence": "EXTRACTED", "source_file": "D:\\opencli\\extension\\src\\background.ts", "source_location": "L12", "weight": 1.0}, {"source": "d_opencli_extension_src_background_ts", "target": "d_opencli_extension_src_identity", "relation": "imports_from", "confidence": "EXTRACTED", "source_file": "D:\\opencli\\extension\\src\\background.ts", "source_location": "L13", "weight": 1.0}, {"source": "d_opencli_extension_src_background_ts", "target": "background_forwardlog", "relation": "contains", "confidence": "EXTRACTED", "source_file": "D:\\opencli\\extension\\src\\background.ts", "source_location": "L26", "weight": 1.0}, {"source": "d_opencli_extension_src_background_ts", "target": "background_connect", "relation": "contains", "confidence": "EXTRACTED", "source_file": "D:\\opencli\\extension\\src\\background.ts", "source_location": "L47", "weight": 1.0}, {"source": "d_opencli_extension_src_background_ts", "target": "background_schedulereconnect", "relation": "contains", "confidence": "EXTRACTED", "source_file": "D:\\opencli\\extension\\src\\background.ts", "source_location": "L107", "weight": 1.0}, {"source": "d_opencli_extension_src_background_ts", "target": "background_getidletimeout", "relation": "contains", "confidence": "EXTRACTED", "source_file": "D:\\opencli\\extension\\src\\background.ts", "source_location": "L140", "weight": 1.0}, {"source": "d_opencli_extension_src_background_ts", "target": "background_getworkspacekey", "relation": "contains", "confidence": "EXTRACTED", "source_file": "D:\\opencli\\extension\\src\\background.ts", "source_location": "L151", "weight": 1.0}, {"source": "d_opencli_extension_src_background_ts", "target": "background_resetwindowidletimer", "relation": "contains", "confidence": "EXTRACTED", "source_file": "D:\\opencli\\extension\\src\\background.ts", "source_location": "L155", "weight": 1.0}, {"source": "d_opencli_extension_src_background_ts", "target": "background_getautomationwindow", "relation": "contains", "confidence": "EXTRACTED", "source_file": "D:\\opencli\\extension\\src\\background.ts", "source_location": "L185", "weight": 1.0}, {"source": "d_opencli_extension_src_background_ts", "target": "background_initialize", "relation": "contains", "confidence": "EXTRACTED", "source_file": "D:\\opencli\\extension\\src\\background.ts", "source_location": "L265", "weight": 1.0}, {"source": "d_opencli_extension_src_background_ts", "target": "background_handlecommand", "relation": "contains", "confidence": "EXTRACTED", "source_file": "D:\\opencli\\extension\\src\\background.ts", "source_location": "L300", "weight": 1.0}, {"source": "d_opencli_extension_src_background_ts", "target": "background_isdebuggableurl", "relation": "contains", "confidence": "EXTRACTED", "source_file": "D:\\opencli\\extension\\src\\background.ts", "source_location": "L355", "weight": 1.0}, {"source": "d_opencli_extension_src_background_ts", "target": "background_issafenavigationurl", "relation": "contains", "confidence": "EXTRACTED", "source_file": "D:\\opencli\\extension\\src\\background.ts", "source_location": "L361", "weight": 1.0}, {"source": "d_opencli_extension_src_background_ts", "target": "background_normalizeurlforcomparison", "relation": "contains", "confidence": "EXTRACTED", "source_file": "D:\\opencli\\extension\\src\\background.ts", "source_location": "L366", "weight": 1.0}, {"source": "d_opencli_extension_src_background_ts", "target": "background_istargeturl", "relation": "contains", "confidence": "EXTRACTED", "source_file": "D:\\opencli\\extension\\src\\background.ts", "source_location": "L380", "weight": 1.0}, {"source": "d_opencli_extension_src_background_ts", "target": "background_matchesdomain", "relation": "contains", "confidence": "EXTRACTED", "source_file": "D:\\opencli\\extension\\src\\background.ts", "source_location": "L384", "weight": 1.0}, {"source": "d_opencli_extension_src_background_ts", "target": "background_matchesbindcriteria", "relation": "contains", "confidence": "EXTRACTED", "source_file": "D:\\opencli\\extension\\src\\background.ts", "source_location": "L394", "weight": 1.0}, {"source": "d_opencli_extension_src_background_ts", "target": "background_setworkspacesession", "relation": "contains", "confidence": "EXTRACTED", "source_file": "D:\\opencli\\extension\\src\\background.ts", "source_location": "L408", "weight": 1.0}, {"source": "d_opencli_extension_src_background_ts", "target": "background_resolvecommandtabid", "relation": "contains", "confidence": "EXTRACTED", "source_file": "D:\\opencli\\extension\\src\\background.ts", "source_location": "L422", "weight": 1.0}, {"source": "d_opencli_extension_src_background_ts", "target": "background_resolvetab", "relation": "contains", "confidence": "EXTRACTED", "source_file": "D:\\opencli\\extension\\src\\background.ts", "source_location": "L433", "weight": 1.0}, {"source": "d_opencli_extension_src_background_ts", "target": "background_pagescopedresult", "relation": "contains", "confidence": "EXTRACTED", "source_file": "D:\\opencli\\extension\\src\\background.ts", "source_location": "L503", "weight": 1.0}, {"source": "d_opencli_extension_src_background_ts", "target": "background_resolvetabid", "relation": "contains", "confidence": "EXTRACTED", "source_file": "D:\\opencli\\extension\\src\\background.ts", "source_location": "L509", "weight": 1.0}, {"source": "d_opencli_extension_src_background_ts", "target": "background_listautomationtabs", "relation": "contains", "confidence": "EXTRACTED", "source_file": "D:\\opencli\\extension\\src\\background.ts", "source_location": "L514", "weight": 1.0}, {"source": "d_opencli_extension_src_background_ts", "target": "background_listautomationwebtabs", "relation": "contains", "confidence": "EXTRACTED", "source_file": "D:\\opencli\\extension\\src\\background.ts", "source_location": "L533", "weight": 1.0}, {"source": "d_opencli_extension_src_background_ts", "target": "background_handleexec", "relation": "contains", "confidence": "EXTRACTED", "source_file": "D:\\opencli\\extension\\src\\background.ts", "source_location": "L538", "weight": 1.0}, {"source": "d_opencli_extension_src_background_ts", "target": "background_handlenavigate", "relation": "contains", "confidence": "EXTRACTED", "source_file": "D:\\opencli\\extension\\src\\background.ts", "source_location": "L551", "weight": 1.0}, {"source": "d_opencli_extension_src_background_ts", "target": "background_handletabs", "relation": "contains", "confidence": "EXTRACTED", "source_file": "D:\\opencli\\extension\\src\\background.ts", "source_location": "L651", "weight": 1.0}, {"source": "d_opencli_extension_src_background_ts", "target": "background_handlecookies", "relation": "contains", "confidence": "EXTRACTED", "source_file": "D:\\opencli\\extension\\src\\background.ts", "source_location": "L717", "weight": 1.0}, {"source": "d_opencli_extension_src_background_ts", "target": "background_handlescreenshot", "relation": "contains", "confidence": "EXTRACTED", "source_file": "D:\\opencli\\extension\\src\\background.ts", "source_location": "L737", "weight": 1.0}, {"source": "d_opencli_extension_src_background_ts", "target": "background_handlecdp", "relation": "contains", "confidence": "EXTRACTED", "source_file": "D:\\opencli\\extension\\src\\background.ts", "source_location": "L776", "weight": 1.0}, {"source": "d_opencli_extension_src_background_ts", "target": "background_handleclosewindow", "relation": "contains", "confidence": "EXTRACTED", "source_file": "D:\\opencli\\extension\\src\\background.ts", "source_location": "L797", "weight": 1.0}, {"source": "d_opencli_extension_src_background_ts", "target": "background_handlesetfileinput", "relation": "contains", "confidence": "EXTRACTED", "source_file": "D:\\opencli\\extension\\src\\background.ts", "source_location": "L814", "weight": 1.0}, {"source": "d_opencli_extension_src_background_ts", "target": "background_handleinserttext", "relation": "contains", "confidence": "EXTRACTED", "source_file": "D:\\opencli\\extension\\src\\background.ts", "source_location": "L828", "weight": 1.0}, {"source": "d_opencli_extension_src_background_ts", "target": "background_handlenetworkcapturestart", "relation": "contains", "confidence": "EXTRACTED", "source_file": "D:\\opencli\\extension\\src\\background.ts", "source_location": "L842", "weight": 1.0}, {"source": "d_opencli_extension_src_background_ts", "target": "background_handlenetworkcaptureread", "relation": "contains", "confidence": "EXTRACTED", "source_file": "D:\\opencli\\extension\\src\\background.ts", "source_location": "L853", "weight": 1.0}, {"source": "d_opencli_extension_src_background_ts", "target": "background_handlesessions", "relation": "contains", "confidence": "EXTRACTED", "source_file": "D:\\opencli\\extension\\src\\background.ts", "source_location": "L864", "weight": 1.0}, {"source": "d_opencli_extension_src_background_ts", "target": "background_handlebindcurrent", "relation": "contains", "confidence": "EXTRACTED", "source_file": "D:\\opencli\\extension\\src\\background.ts", "source_location": "L875", "weight": 1.0}, {"source": "background_connect", "target": "background_schedulereconnect", "relation": "calls", "confidence": "EXTRACTED", "source_file": "D:\\opencli\\extension\\src\\background.ts", "source_location": "L60", "weight": 1.0}, {"source": "background_resetwindowidletimer", "target": "background_getidletimeout", "relation": "calls", "confidence": "EXTRACTED", "source_file": "D:\\opencli\\extension\\src\\background.ts", "source_location": "L159", "weight": 1.0}, {"source": "background_getautomationwindow", "target": "background_issafenavigationurl", "relation": "calls", "confidence": "EXTRACTED", "source_file": "D:\\opencli\\extension\\src\\background.ts", "source_location": "L199", "weight": 1.0}, {"source": "background_getautomationwindow", "target": "background_getidletimeout", "relation": "calls", "confidence": "EXTRACTED", "source_file": "D:\\opencli\\extension\\src\\background.ts", "source_location": "L213", "weight": 1.0}, {"source": "background_getautomationwindow", "target": "background_resetwindowidletimer", "relation": "calls", "confidence": "EXTRACTED", "source_file": "D:\\opencli\\extension\\src\\background.ts", "source_location": "L219", "weight": 1.0}, {"source": "background_initialize", "target": "background_connect", "relation": "calls", "confidence": "EXTRACTED", "source_file": "D:\\opencli\\extension\\src\\background.ts", "source_location": "L270", "weight": 1.0}, {"source": "background_handlecommand", "target": "background_getworkspacekey", "relation": "calls", "confidence": "EXTRACTED", "source_file": "D:\\opencli\\extension\\src\\background.ts", "source_location": "L301", "weight": 1.0}, {"source": "background_handlecommand", "target": "background_resetwindowidletimer", "relation": "calls", "confidence": "EXTRACTED", "source_file": "D:\\opencli\\extension\\src\\background.ts", "source_location": "L308", "weight": 1.0}, {"source": "background_handlecommand", "target": "background_handleexec", "relation": "calls", "confidence": "EXTRACTED", "source_file": "D:\\opencli\\extension\\src\\background.ts", "source_location": "L312", "weight": 1.0}, {"source": "background_handlecommand", "target": "background_handlenavigate", "relation": "calls", "confidence": "EXTRACTED", "source_file": "D:\\opencli\\extension\\src\\background.ts", "source_location": "L314", "weight": 1.0}, {"source": "background_handlecommand", "target": "background_handletabs", "relation": "calls", "confidence": "EXTRACTED", "source_file": "D:\\opencli\\extension\\src\\background.ts", "source_location": "L316", "weight": 1.0}, {"source": "background_handlecommand", "target": "background_handlecookies", "relation": "calls", "confidence": "EXTRACTED", "source_file": "D:\\opencli\\extension\\src\\background.ts", "source_location": "L318", "weight": 1.0}, {"source": "background_handlecommand", "target": "background_handlescreenshot", "relation": "calls", "confidence": "EXTRACTED", "source_file": "D:\\opencli\\extension\\src\\background.ts", "source_location": "L320", "weight": 1.0}, {"source": "background_handlecommand", "target": "background_handleclosewindow", "relation": "calls", "confidence": "EXTRACTED", "source_file": "D:\\opencli\\extension\\src\\background.ts", "source_location": "L322", "weight": 1.0}, {"source": "background_handlecommand", "target": "background_handlecdp", "relation": "calls", "confidence": "EXTRACTED", "source_file": "D:\\opencli\\extension\\src\\background.ts", "source_location": "L324", "weight": 1.0}, {"source": "background_handlecommand", "target": "background_handlesessions", "relation": "calls", "confidence": "EXTRACTED", "source_file": "D:\\opencli\\extension\\src\\background.ts", "source_location": "L326", "weight": 1.0}, {"source": "background_handlecommand", "target": "background_handlesetfileinput", "relation": "calls", "confidence": "EXTRACTED", "source_file": "D:\\opencli\\extension\\src\\background.ts", "source_location": "L328", "weight": 1.0}, {"source": "background_handlecommand", "target": "background_handleinserttext", "relation": "calls", "confidence": "EXTRACTED", "source_file": "D:\\opencli\\extension\\src\\background.ts", "source_location": "L330", "weight": 1.0}, {"source": "background_handlecommand", "target": "background_handlebindcurrent", "relation": "calls", "confidence": "EXTRACTED", "source_file": "D:\\opencli\\extension\\src\\background.ts", "source_location": "L332", "weight": 1.0}, {"source": "background_handlecommand", "target": "background_handlenetworkcapturestart", "relation": "calls", "confidence": "EXTRACTED", "source_file": "D:\\opencli\\extension\\src\\background.ts", "source_location": "L334", "weight": 1.0}, {"source": "background_handlecommand", "target": "background_handlenetworkcaptureread", "relation": "calls", "confidence": "EXTRACTED", "source_file": "D:\\opencli\\extension\\src\\background.ts", "source_location": "L336", "weight": 1.0}, {"source": "background_istargeturl", "target": "background_normalizeurlforcomparison", "relation": "calls", "confidence": "EXTRACTED", "source_file": "D:\\opencli\\extension\\src\\background.ts", "source_location": "L381", "weight": 1.0}, {"source": "background_matchesbindcriteria", "target": "background_isdebuggableurl", "relation": "calls", "confidence": "EXTRACTED", "source_file": "D:\\opencli\\extension\\src\\background.ts", "source_location": "L395", "weight": 1.0}, {"source": "background_matchesbindcriteria", "target": "background_matchesdomain", "relation": "calls", "confidence": "EXTRACTED", "source_file": "D:\\opencli\\extension\\src\\background.ts", "source_location": "L396", "weight": 1.0}, {"source": "background_setworkspacesession", "target": "background_getidletimeout", "relation": "calls", "confidence": "EXTRACTED", "source_file": "D:\\opencli\\extension\\src\\background.ts", "source_location": "L414", "weight": 1.0}, {"source": "background_resolvecommandtabid", "target": "background_resolvetabid", "relation": "calls", "confidence": "EXTRACTED", "source_file": "D:\\opencli\\extension\\src\\background.ts", "source_location": "L423", "weight": 1.0}, {"source": "background_resolvetab", "target": "background_isdebuggableurl", "relation": "calls", "confidence": "EXTRACTED", "source_file": "D:\\opencli\\extension\\src\\background.ts", "source_location": "L442", "weight": 1.0}, {"source": "background_resolvetab", "target": "background_getautomationwindow", "relation": "calls", "confidence": "EXTRACTED", "source_file": "D:\\opencli\\extension\\src\\background.ts", "source_location": "L475", "weight": 1.0}, {"source": "background_resolvetabid", "target": "background_resolvetab", "relation": "calls", "confidence": "EXTRACTED", "source_file": "D:\\opencli\\extension\\src\\background.ts", "source_location": "L510", "weight": 1.0}, {"source": "background_listautomationwebtabs", "target": "background_listautomationtabs", "relation": "calls", "confidence": "EXTRACTED", "source_file": "D:\\opencli\\extension\\src\\background.ts", "source_location": "L534", "weight": 1.0}, {"source": "background_handleexec", "target": "background_resolvecommandtabid", "relation": "calls", "confidence": "EXTRACTED", "source_file": "D:\\opencli\\extension\\src\\background.ts", "source_location": "L540", "weight": 1.0}, {"source": "background_handleexec", "target": "background_resolvetabid", "relation": "calls", "confidence": "EXTRACTED", "source_file": "D:\\opencli\\extension\\src\\background.ts", "source_location": "L541", "weight": 1.0}, {"source": "background_handleexec", "target": "background_pagescopedresult", "relation": "calls", "confidence": "EXTRACTED", "source_file": "D:\\opencli\\extension\\src\\background.ts", "source_location": "L545", "weight": 1.0}, {"source": "background_handlenavigate", "target": "background_issafenavigationurl", "relation": "calls", "confidence": "EXTRACTED", "source_file": "D:\\opencli\\extension\\src\\background.ts", "source_location": "L553", "weight": 1.0}, {"source": "background_handlenavigate", "target": "background_resolvecommandtabid", "relation": "calls", "confidence": "EXTRACTED", "source_file": "D:\\opencli\\extension\\src\\background.ts", "source_location": "L557", "weight": 1.0}, {"source": "background_handlenavigate", "target": "background_resolvetab", "relation": "calls", "confidence": "EXTRACTED", "source_file": "D:\\opencli\\extension\\src\\background.ts", "source_location": "L558", "weight": 1.0}, {"source": "background_handlenavigate", "target": "background_normalizeurlforcomparison", "relation": "calls", "confidence": "EXTRACTED", "source_file": "D:\\opencli\\extension\\src\\background.ts", "source_location": "L562", "weight": 1.0}, {"source": "background_handlenavigate", "target": "background_istargeturl", "relation": "calls", "confidence": "EXTRACTED", "source_file": "D:\\opencli\\extension\\src\\background.ts", "source_location": "L566", "weight": 1.0}, {"source": "background_handlenavigate", "target": "background_pagescopedresult", "relation": "calls", "confidence": "EXTRACTED", "source_file": "D:\\opencli\\extension\\src\\background.ts", "source_location": "L567", "weight": 1.0}, {"source": "background_handletabs", "target": "background_listautomationwebtabs", "relation": "calls", "confidence": "EXTRACTED", "source_file": "D:\\opencli\\extension\\src\\background.ts", "source_location": "L654", "weight": 1.0}, {"source": "background_handletabs", "target": "background_issafenavigationurl", "relation": "calls", "confidence": "EXTRACTED", "source_file": "D:\\opencli\\extension\\src\\background.ts", "source_location": "L663", "weight": 1.0}, {"source": "background_handletabs", "target": "background_getautomationwindow", "relation": "calls", "confidence": "EXTRACTED", "source_file": "D:\\opencli\\extension\\src\\background.ts", "source_location": "L666", "weight": 1.0}, {"source": "background_handletabs", "target": "background_pagescopedresult", "relation": "calls", "confidence": "EXTRACTED", "source_file": "D:\\opencli\\extension\\src\\background.ts", "source_location": "L669", "weight": 1.0}, {"source": "background_handletabs", "target": "background_resolvecommandtabid", "relation": "calls", "confidence": "EXTRACTED", "source_file": "D:\\opencli\\extension\\src\\background.ts", "source_location": "L681", "weight": 1.0}, {"source": "background_handletabs", "target": "background_resolvetabid", "relation": "calls", "confidence": "EXTRACTED", "source_file": "D:\\opencli\\extension\\src\\background.ts", "source_location": "L682", "weight": 1.0}, {"source": "background_handlescreenshot", "target": "background_resolvecommandtabid", "relation": "calls", "confidence": "EXTRACTED", "source_file": "D:\\opencli\\extension\\src\\background.ts", "source_location": "L738", "weight": 1.0}, {"source": "background_handlescreenshot", "target": "background_resolvetabid", "relation": "calls", "confidence": "EXTRACTED", "source_file": "D:\\opencli\\extension\\src\\background.ts", "source_location": "L739", "weight": 1.0}, {"source": "background_handlescreenshot", "target": "background_pagescopedresult", "relation": "calls", "confidence": "EXTRACTED", "source_file": "D:\\opencli\\extension\\src\\background.ts", "source_location": "L746", "weight": 1.0}, {"source": "background_handlecdp", "target": "background_resolvecommandtabid", "relation": "calls", "confidence": "EXTRACTED", "source_file": "D:\\opencli\\extension\\src\\background.ts", "source_location": "L781", "weight": 1.0}, {"source": "background_handlecdp", "target": "background_resolvetabid", "relation": "calls", "confidence": "EXTRACTED", "source_file": "D:\\opencli\\extension\\src\\background.ts", "source_location": "L782", "weight": 1.0}, {"source": "background_handlecdp", "target": "background_pagescopedresult", "relation": "calls", "confidence": "EXTRACTED", "source_file": "D:\\opencli\\extension\\src\\background.ts", "source_location": "L791", "weight": 1.0}, {"source": "background_handlesetfileinput", "target": "background_resolvecommandtabid", "relation": "calls", "confidence": "EXTRACTED", "source_file": "D:\\opencli\\extension\\src\\background.ts", "source_location": "L818", "weight": 1.0}, {"source": "background_handlesetfileinput", "target": "background_resolvetabid", "relation": "calls", "confidence": "EXTRACTED", "source_file": "D:\\opencli\\extension\\src\\background.ts", "source_location": "L819", "weight": 1.0}, {"source": "background_handlesetfileinput", "target": "background_pagescopedresult", "relation": "calls", "confidence": "EXTRACTED", "source_file": "D:\\opencli\\extension\\src\\background.ts", "source_location": "L822", "weight": 1.0}, {"source": "background_handleinserttext", "target": "background_resolvecommandtabid", "relation": "calls", "confidence": "EXTRACTED", "source_file": "D:\\opencli\\extension\\src\\background.ts", "source_location": "L832", "weight": 1.0}, {"source": "background_handleinserttext", "target": "background_resolvetabid", "relation": "calls", "confidence": "EXTRACTED", "source_file": "D:\\opencli\\extension\\src\\background.ts", "source_location": "L833", "weight": 1.0}, {"source": "background_handleinserttext", "target": "background_pagescopedresult", "relation": "calls", "confidence": "EXTRACTED", "source_file": "D:\\opencli\\extension\\src\\background.ts", "source_location": "L836", "weight": 1.0}, {"source": "background_handlenetworkcapturestart", "target": "background_resolvecommandtabid", "relation": "calls", "confidence": "EXTRACTED", "source_file": "D:\\opencli\\extension\\src\\background.ts", "source_location": "L843", "weight": 1.0}, {"source": "background_handlenetworkcapturestart", "target": "background_resolvetabid", "relation": "calls", "confidence": "EXTRACTED", "source_file": "D:\\opencli\\extension\\src\\background.ts", "source_location": "L844", "weight": 1.0}, {"source": "background_handlenetworkcapturestart", "target": "background_pagescopedresult", "relation": "calls", "confidence": "EXTRACTED", "source_file": "D:\\opencli\\extension\\src\\background.ts", "source_location": "L847", "weight": 1.0}, {"source": "background_handlenetworkcaptureread", "target": "background_resolvecommandtabid", "relation": "calls", "confidence": "EXTRACTED", "source_file": "D:\\opencli\\extension\\src\\background.ts", "source_location": "L854", "weight": 1.0}, {"source": "background_handlenetworkcaptureread", "target": "background_resolvetabid", "relation": "calls", "confidence": "EXTRACTED", "source_file": "D:\\opencli\\extension\\src\\background.ts", "source_location": "L855", "weight": 1.0}, {"source": "background_handlenetworkcaptureread", "target": "background_pagescopedresult", "relation": "calls", "confidence": "EXTRACTED", "source_file": "D:\\opencli\\extension\\src\\background.ts", "source_location": "L858", "weight": 1.0}, {"source": "background_handlebindcurrent", "target": "background_setworkspacesession", "relation": "calls", "confidence": "EXTRACTED", "source_file": "D:\\opencli\\extension\\src\\background.ts", "source_location": "L892", "weight": 1.0}, {"source": "background_handlebindcurrent", "target": "background_resetwindowidletimer", "relation": "calls", "confidence": "EXTRACTED", "source_file": "D:\\opencli\\extension\\src\\background.ts", "source_location": "L897", "weight": 1.0}, {"source": "background_handlebindcurrent", "target": "background_pagescopedresult", "relation": "calls", "confidence": "EXTRACTED", "source_file": "D:\\opencli\\extension\\src\\background.ts", "source_location": "L899", "weight": 1.0}], "raw_calls": [{"caller_nid": "background_forwardlog", "callee": "join", "source_file": "D:\\opencli\\extension\\src\\background.ts", "source_location": "L29"}, {"caller_nid": "background_forwardlog", "callee": "map", "source_file": "D:\\opencli\\extension\\src\\background.ts", "source_location": "L29"}, {"caller_nid": "background_forwardlog", "callee": "send", "source_file": "D:\\opencli\\extension\\src\\background.ts", "source_location": "L30"}, {"caller_nid": "background_forwardlog", "callee": "stringify", "source_file": "D:\\opencli\\extension\\src\\background.ts", "source_location": "L30"}, {"caller_nid": "background_forwardlog", "callee": "now", "source_file": "D:\\opencli\\extension\\src\\background.ts", "source_location": "L30"}, {"caller_nid": "background_connect", "callee": "fetch", "source_file": "D:\\opencli\\extension\\src\\background.ts", "source_location": "L51"}, {"caller_nid": "background_connect", "callee": "timeout", "source_file": "D:\\opencli\\extension\\src\\background.ts", "source_location": "L51"}, {"caller_nid": "background_schedulereconnect", "callee": "min", "source_file": "D:\\opencli\\extension\\src\\background.ts", "source_location": "L111"}, {"caller_nid": "background_schedulereconnect", "callee": "pow", "source_file": "D:\\opencli\\extension\\src\\background.ts", "source_location": "L111"}, {"caller_nid": "background_schedulereconnect", "callee": "setTimeout", "source_file": "D:\\opencli\\extension\\src\\background.ts", "source_location": "L112"}, {"caller_nid": "background_getidletimeout", "callee": "get", "source_file": "D:\\opencli\\extension\\src\\background.ts", "source_location": "L141"}, {"caller_nid": "background_getidletimeout", "callee": "startsWith", "source_file": "D:\\opencli\\extension\\src\\background.ts", "source_location": "L143"}, {"caller_nid": "background_getidletimeout", "callee": "startsWith", "source_file": "D:\\opencli\\extension\\src\\background.ts", "source_location": "L143"}, {"caller_nid": "background_getworkspacekey", "callee": "trim", "source_file": "D:\\opencli\\extension\\src\\background.ts", "source_location": "L152"}, {"caller_nid": "background_resetwindowidletimer", "callee": "get", "source_file": "D:\\opencli\\extension\\src\\background.ts", "source_location": "L156"}, {"caller_nid": "background_resetwindowidletimer", "callee": "clearTimeout", "source_file": "D:\\opencli\\extension\\src\\background.ts", "source_location": "L158"}, {"caller_nid": "background_resetwindowidletimer", "callee": "now", "source_file": "D:\\opencli\\extension\\src\\background.ts", "source_location": "L160"}, {"caller_nid": "background_resetwindowidletimer", "callee": "setTimeout", "source_file": "D:\\opencli\\extension\\src\\background.ts", "source_location": "L161"}, {"caller_nid": "background_getautomationwindow", "callee": "get", "source_file": "D:\\opencli\\extension\\src\\background.ts", "source_location": "L187"}, {"caller_nid": "background_getautomationwindow", "callee": "get", "source_file": "D:\\opencli\\extension\\src\\background.ts", "source_location": "L190"}, {"caller_nid": "background_getautomationwindow", "callee": "delete", "source_file": "D:\\opencli\\extension\\src\\background.ts", "source_location": "L194"}, {"caller_nid": "background_getautomationwindow", "callee": "create", "source_file": "D:\\opencli\\extension\\src\\background.ts", "source_location": "L203"}, {"caller_nid": "background_getautomationwindow", "callee": "now", "source_file": "D:\\opencli\\extension\\src\\background.ts", "source_location": "L213"}, {"caller_nid": "background_getautomationwindow", "callee": "set", "source_file": "D:\\opencli\\extension\\src\\background.ts", "source_location": "L217"}, {"caller_nid": "background_getautomationwindow", "callee": "log", "source_file": "D:\\opencli\\extension\\src\\background.ts", "source_location": "L218"}, {"caller_nid": "background_getautomationwindow", "callee": "query", "source_file": "D:\\opencli\\extension\\src\\background.ts", "source_location": "L221"}, {"caller_nid": "background_initialize", "callee": "create", "source_file": "D:\\opencli\\extension\\src\\background.ts", "source_location": "L268"}, {"caller_nid": "background_initialize", "callee": "registerListeners", "source_file": "D:\\opencli\\extension\\src\\background.ts", "source_location": "L269"}, {"caller_nid": "background_initialize", "callee": "log", "source_file": "D:\\opencli\\extension\\src\\background.ts", "source_location": "L271"}, {"caller_nid": "background_handlecommand", "callee": "set", "source_file": "D:\\opencli\\extension\\src\\background.ts", "source_location": "L305"}, {"caller_nid": "background_handlecommand", "callee": "String", "source_file": "D:\\opencli\\extension\\src\\background.ts", "source_location": "L344"}, {"caller_nid": "background_isdebuggableurl", "callee": "startsWith", "source_file": "D:\\opencli\\extension\\src\\background.ts", "source_location": "L357"}, {"caller_nid": "background_isdebuggableurl", "callee": "startsWith", "source_file": "D:\\opencli\\extension\\src\\background.ts", "source_location": "L357"}, {"caller_nid": "background_isdebuggableurl", "callee": "startsWith", "source_file": "D:\\opencli\\extension\\src\\background.ts", "source_location": "L357"}, {"caller_nid": "background_issafenavigationurl", "callee": "startsWith", "source_file": "D:\\opencli\\extension\\src\\background.ts", "source_location": "L362"}, {"caller_nid": "background_issafenavigationurl", "callee": "startsWith", "source_file": "D:\\opencli\\extension\\src\\background.ts", "source_location": "L362"}, {"caller_nid": "background_matchesdomain", "callee": "endsWith", "source_file": "D:\\opencli\\extension\\src\\background.ts", "source_location": "L388"}, {"caller_nid": "background_matchesbindcriteria", "callee": "startsWith", "source_file": "D:\\opencli\\extension\\src\\background.ts", "source_location": "L400"}, {"caller_nid": "background_setworkspacesession", "callee": "get", "source_file": "D:\\opencli\\extension\\src\\background.ts", "source_location": "L409"}, {"caller_nid": "background_setworkspacesession", "callee": "clearTimeout", "source_file": "D:\\opencli\\extension\\src\\background.ts", "source_location": "L410"}, {"caller_nid": "background_setworkspacesession", "callee": "set", "source_file": "D:\\opencli\\extension\\src\\background.ts", "source_location": "L411"}, {"caller_nid": "background_setworkspacesession", "callee": "now", "source_file": "D:\\opencli\\extension\\src\\background.ts", "source_location": "L414"}, {"caller_nid": "background_resolvetab", "callee": "get", "source_file": "D:\\opencli\\extension\\src\\background.ts", "source_location": "L437"}, {"caller_nid": "background_resolvetab", "callee": "get", "source_file": "D:\\opencli\\extension\\src\\background.ts", "source_location": "L438"}, {"caller_nid": "background_resolvetab", "callee": "warn", "source_file": "D:\\opencli\\extension\\src\\background.ts", "source_location": "L446"}, {"caller_nid": "background_resolvetab", "callee": "move", "source_file": "D:\\opencli\\extension\\src\\background.ts", "source_location": "L448"}, {"caller_nid": "background_resolvetab", "callee": "get", "source_file": "D:\\opencli\\extension\\src\\background.ts", "source_location": "L449"}, {"caller_nid": "background_resolvetab", "callee": "warn", "source_file": "D:\\opencli\\extension\\src\\background.ts", "source_location": "L454"}, {"caller_nid": "background_resolvetab", "callee": "warn", "source_file": "D:\\opencli\\extension\\src\\background.ts", "source_location": "L457"}, {"caller_nid": "background_resolvetab", "callee": "warn", "source_file": "D:\\opencli\\extension\\src\\background.ts", "source_location": "L460"}, {"caller_nid": "background_resolvetab", "callee": "get", "source_file": "D:\\opencli\\extension\\src\\background.ts", "source_location": "L464"}, {"caller_nid": "background_resolvetab", "callee": "get", "source_file": "D:\\opencli\\extension\\src\\background.ts", "source_location": "L467"}, {"caller_nid": "background_resolvetab", "callee": "delete", "source_file": "D:\\opencli\\extension\\src\\background.ts", "source_location": "L470"}, {"caller_nid": "background_resolvetab", "callee": "query", "source_file": "D:\\opencli\\extension\\src\\background.ts", "source_location": "L478"}, {"caller_nid": "background_resolvetab", "callee": "find", "source_file": "D:\\opencli\\extension\\src\\background.ts", "source_location": "L479"}, {"caller_nid": "background_resolvetab", "callee": "find", "source_file": "D:\\opencli\\extension\\src\\background.ts", "source_location": "L483"}, {"caller_nid": "background_resolvetab", "callee": "update", "source_file": "D:\\opencli\\extension\\src\\background.ts", "source_location": "L485"}, {"caller_nid": "background_resolvetab", "callee": "get", "source_file": "D:\\opencli\\extension\\src\\background.ts", "source_location": "L488"}, {"caller_nid": "background_resolvetab", "callee": "warn", "source_file": "D:\\opencli\\extension\\src\\background.ts", "source_location": "L490"}, {"caller_nid": "background_resolvetab", "callee": "create", "source_file": "D:\\opencli\\extension\\src\\background.ts", "source_location": "L497"}, {"caller_nid": "background_pagescopedresult", "callee": "resolveTargetId", "source_file": "D:\\opencli\\extension\\src\\background.ts", "source_location": "L504"}, {"caller_nid": "background_listautomationtabs", "callee": "get", "source_file": "D:\\opencli\\extension\\src\\background.ts", "source_location": "L515"}, {"caller_nid": "background_listautomationtabs", "callee": "get", "source_file": "D:\\opencli\\extension\\src\\background.ts", "source_location": "L519"}, {"caller_nid": "background_listautomationtabs", "callee": "delete", "source_file": "D:\\opencli\\extension\\src\\background.ts", "source_location": "L521"}, {"caller_nid": "background_listautomationtabs", "callee": "query", "source_file": "D:\\opencli\\extension\\src\\background.ts", "source_location": "L526"}, {"caller_nid": "background_listautomationtabs", "callee": "delete", "source_file": "D:\\opencli\\extension\\src\\background.ts", "source_location": "L528"}, {"caller_nid": "background_listautomationwebtabs", "callee": "filter", "source_file": "D:\\opencli\\extension\\src\\background.ts", "source_location": "L535"}, {"caller_nid": "background_handleexec", "callee": "startsWith", "source_file": "D:\\opencli\\extension\\src\\background.ts", "source_location": "L543"}, {"caller_nid": "background_handleexec", "callee": "startsWith", "source_file": "D:\\opencli\\extension\\src\\background.ts", "source_location": "L543"}, {"caller_nid": "background_handleexec", "callee": "evaluateAsync", "source_file": "D:\\opencli\\extension\\src\\background.ts", "source_location": "L544"}, {"caller_nid": "background_handleexec", "callee": "String", "source_file": "D:\\opencli\\extension\\src\\background.ts", "source_location": "L547"}, {"caller_nid": "background_handlenavigate", "callee": "get", "source_file": "D:\\opencli\\extension\\src\\background.ts", "source_location": "L561"}, {"caller_nid": "background_handlenavigate", "callee": "hasActiveNetworkCapture", "source_file": "D:\\opencli\\extension\\src\\background.ts", "source_location": "L578"}, {"caller_nid": "background_handlenavigate", "callee": "detach", "source_file": "D:\\opencli\\extension\\src\\background.ts", "source_location": "L579"}, {"caller_nid": "background_handlenavigate", "callee": "update", "source_file": "D:\\opencli\\extension\\src\\background.ts", "source_location": "L582"}, {"caller_nid": "background_handlenavigate", "callee": "get", "source_file": "D:\\opencli\\extension\\src\\background.ts", "source_location": "L632"}, {"caller_nid": "background_handlenavigate", "callee": "get", "source_file": "D:\\opencli\\extension\\src\\background.ts", "source_location": "L637"}, {"caller_nid": "background_handlenavigate", "callee": "warn", "source_file": "D:\\opencli\\extension\\src\\background.ts", "source_location": "L639"}, {"caller_nid": "background_handlenavigate", "callee": "move", "source_file": "D:\\opencli\\extension\\src\\background.ts", "source_location": "L641"}, {"caller_nid": "background_handlenavigate", "callee": "get", "source_file": "D:\\opencli\\extension\\src\\background.ts", "source_location": "L642"}, {"caller_nid": "background_handlenavigate", "callee": "warn", "source_file": "D:\\opencli\\extension\\src\\background.ts", "source_location": "L644"}, {"caller_nid": "background_handletabs", "callee": "all", "source_file": "D:\\opencli\\extension\\src\\background.ts", "source_location": "L655"}, {"caller_nid": "background_handletabs", "callee": "map", "source_file": "D:\\opencli\\extension\\src\\background.ts", "source_location": "L655"}, {"caller_nid": "background_handletabs", "callee": "create", "source_file": "D:\\opencli\\extension\\src\\background.ts", "source_location": "L667"}, {"caller_nid": "background_handletabs", "callee": "catch", "source_file": "D:\\opencli\\extension\\src\\background.ts", "source_location": "L676"}, {"caller_nid": "background_handletabs", "callee": "resolveTargetId", "source_file": "D:\\opencli\\extension\\src\\background.ts", "source_location": "L676"}, {"caller_nid": "background_handletabs", "callee": "remove", "source_file": "D:\\opencli\\extension\\src\\background.ts", "source_location": "L677"}, {"caller_nid": "background_handletabs", "callee": "detach", "source_file": "D:\\opencli\\extension\\src\\background.ts", "source_location": "L678"}, {"caller_nid": "background_handletabs", "callee": "catch", "source_file": "D:\\opencli\\extension\\src\\background.ts", "source_location": "L683"}, {"caller_nid": "background_handletabs", "callee": "resolveTargetId", "source_file": "D:\\opencli\\extension\\src\\background.ts", "source_location": "L683"}, {"caller_nid": "background_handletabs", "callee": "remove", "source_file": "D:\\opencli\\extension\\src\\background.ts", "source_location": "L684"}, {"caller_nid": "background_handletabs", "callee": "detach", "source_file": "D:\\opencli\\extension\\src\\background.ts", "source_location": "L685"}, {"caller_nid": "background_handletabs", "callee": "get", "source_file": "D:\\opencli\\extension\\src\\background.ts", "source_location": "L693"}, {"caller_nid": "background_handletabs", "callee": "get", "source_file": "D:\\opencli\\extension\\src\\background.ts", "source_location": "L696"}, {"caller_nid": "background_handletabs", "callee": "update", "source_file": "D:\\opencli\\extension\\src\\background.ts", "source_location": "L703"}, {"caller_nid": "background_handletabs", "callee": "update", "source_file": "D:\\opencli\\extension\\src\\background.ts", "source_location": "L709"}, {"caller_nid": "background_handlecookies", "callee": "getAll", "source_file": "D:\\opencli\\extension\\src\\background.ts", "source_location": "L724"}, {"caller_nid": "background_handlecookies", "callee": "map", "source_file": "D:\\opencli\\extension\\src\\background.ts", "source_location": "L725"}, {"caller_nid": "background_handlescreenshot", "callee": "screenshot", "source_file": "D:\\opencli\\extension\\src\\background.ts", "source_location": "L741"}, {"caller_nid": "background_handlescreenshot", "callee": "String", "source_file": "D:\\opencli\\extension\\src\\background.ts", "source_location": "L748"}, {"caller_nid": "background_handlecdp", "callee": "has", "source_file": "D:\\opencli\\extension\\src\\background.ts", "source_location": "L778"}, {"caller_nid": "background_handlecdp", "callee": "startsWith", "source_file": "D:\\opencli\\extension\\src\\background.ts", "source_location": "L784"}, {"caller_nid": "background_handlecdp", "callee": "startsWith", "source_file": "D:\\opencli\\extension\\src\\background.ts", "source_location": "L784"}, {"caller_nid": "background_handlecdp", "callee": "ensureAttached", "source_file": "D:\\opencli\\extension\\src\\background.ts", "source_location": "L785"}, {"caller_nid": "background_handlecdp", "callee": "sendCommand", "source_file": "D:\\opencli\\extension\\src\\background.ts", "source_location": "L786"}, {"caller_nid": "background_handlecdp", "callee": "String", "source_file": "D:\\opencli\\extension\\src\\background.ts", "source_location": "L793"}, {"caller_nid": "background_handleclosewindow", "callee": "get", "source_file": "D:\\opencli\\extension\\src\\background.ts", "source_location": "L798"}, {"caller_nid": "background_handleclosewindow", "callee": "remove", "source_file": "D:\\opencli\\extension\\src\\background.ts", "source_location": "L802"}, {"caller_nid": "background_handleclosewindow", "callee": "clearTimeout", "source_file": "D:\\opencli\\extension\\src\\background.ts", "source_location": "L807"}, {"caller_nid": "background_handleclosewindow", "callee": "delete", "source_file": "D:\\opencli\\extension\\src\\background.ts", "source_location": "L808"}, {"caller_nid": "background_handleclosewindow", "callee": "delete", "source_file": "D:\\opencli\\extension\\src\\background.ts", "source_location": "L809"}, {"caller_nid": "background_handlesetfileinput", "callee": "isArray", "source_file": "D:\\opencli\\extension\\src\\background.ts", "source_location": "L815"}, {"caller_nid": "background_handlesetfileinput", "callee": "setFileInputFiles", "source_file": "D:\\opencli\\extension\\src\\background.ts", "source_location": "L821"}, {"caller_nid": "background_handlesetfileinput", "callee": "String", "source_file": "D:\\opencli\\extension\\src\\background.ts", "source_location": "L824"}, {"caller_nid": "background_handleinserttext", "callee": "insertText", "source_file": "D:\\opencli\\extension\\src\\background.ts", "source_location": "L835"}, {"caller_nid": "background_handleinserttext", "callee": "String", "source_file": "D:\\opencli\\extension\\src\\background.ts", "source_location": "L838"}, {"caller_nid": "background_handlenetworkcapturestart", "callee": "startNetworkCapture", "source_file": "D:\\opencli\\extension\\src\\background.ts", "source_location": "L846"}, {"caller_nid": "background_handlenetworkcapturestart", "callee": "String", "source_file": "D:\\opencli\\extension\\src\\background.ts", "source_location": "L849"}, {"caller_nid": "background_handlenetworkcaptureread", "callee": "readNetworkCapture", "source_file": "D:\\opencli\\extension\\src\\background.ts", "source_location": "L857"}, {"caller_nid": "background_handlenetworkcaptureread", "callee": "String", "source_file": "D:\\opencli\\extension\\src\\background.ts", "source_location": "L860"}, {"caller_nid": "background_handlesessions", "callee": "now", "source_file": "D:\\opencli\\extension\\src\\background.ts", "source_location": "L865"}, {"caller_nid": "background_handlesessions", "callee": "all", "source_file": "D:\\opencli\\extension\\src\\background.ts", "source_location": "L866"}, {"caller_nid": "background_handlesessions", "callee": "map", "source_file": "D:\\opencli\\extension\\src\\background.ts", "source_location": "L866"}, {"caller_nid": "background_handlesessions", "callee": "entries", "source_file": "D:\\opencli\\extension\\src\\background.ts", "source_location": "L866"}, {"caller_nid": "background_handlebindcurrent", "callee": "query", "source_file": "D:\\opencli\\extension\\src\\background.ts", "source_location": "L876"}, {"caller_nid": "background_handlebindcurrent", "callee": "query", "source_file": "D:\\opencli\\extension\\src\\background.ts", "source_location": "L877"}, {"caller_nid": "background_handlebindcurrent", "callee": "query", "source_file": "D:\\opencli\\extension\\src\\background.ts", "source_location": "L878"}, {"caller_nid": "background_handlebindcurrent", "callee": "find", "source_file": "D:\\opencli\\extension\\src\\background.ts", "source_location": "L879"}, {"caller_nid": "background_handlebindcurrent", "callee": "find", "source_file": "D:\\opencli\\extension\\src\\background.ts", "source_location": "L880"}, {"caller_nid": "background_handlebindcurrent", "callee": "find", "source_file": "D:\\opencli\\extension\\src\\background.ts", "source_location": "L881"}, {"caller_nid": "background_handlebindcurrent", "callee": "log", "source_file": "D:\\opencli\\extension\\src\\background.ts", "source_location": "L898"}]}