{"nodes": [{"id": "d_opencli_clis_discord_app_delete_js", "label": "delete.js", "file_type": "code", "source_file": "D:\\opencli\\clis\\discord-app\\delete.js", "source_location": "L1"}, {"id": "delete_builddeletescript", "label": "buildDeleteScript()", "file_type": "code", "source_file": "D:\\opencli\\clis\\discord-app\\delete.js", "source_location": "L4"}], "edges": [{"source": "d_opencli_clis_discord_app_delete_js", "target": "registry", "relation": "imports_from", "confidence": "EXTRACTED", "source_file": "D:\\opencli\\clis\\discord-app\\delete.js", "source_location": "L1", "weight": 1.0}, {"source": "d_opencli_clis_discord_app_delete_js", "target": "errors", "relation": "imports_from", "confidence": "EXTRACTED", "source_file": "D:\\opencli\\clis\\discord-app\\delete.js", "source_location": "L2", "weight": 1.0}, {"source": "d_opencli_clis_discord_app_delete_js", "target": "delete_builddeletescript", "relation": "contains", "confidence": "EXTRACTED", "source_file": "D:\\opencli\\clis\\discord-app\\delete.js", "source_location": "L4", "weight": 1.0}], "raw_calls": [{"caller_nid": "delete_builddeletescript", "callee": "stringify", "source_file": "D:\\opencli\\clis\\discord-app\\delete.js", "source_location": "L7"}]}