{"nodes": [{"id": "d_opencli_clis_douyin_videos_shared_whisper_transcriber_js", "label": "whisper-transcriber.js", "file_type": "code", "source_file": "D:\\opencli\\clis\\douyin-videos\\_shared\\whisper-transcriber.js", "source_location": "L1"}, {"id": "whisper_transcriber_deduplicatetranscripttext", "label": "deduplicateTranscriptText()", "file_type": "code", "source_file": "D:\\opencli\\clis\\douyin-videos\\_shared\\whisper-transcriber.js", "source_location": "L12"}, {"id": "whisper_transcriber_gettimeoutoptions", "label": "getTimeoutOptions()", "file_type": "code", "source_file": "D:\\opencli\\clis\\douyin-videos\\_shared\\whisper-transcriber.js", "source_location": "L30"}, {"id": "whisper_transcriber_checkgpuavailable", "label": "checkGPUAvailable()", "file_type": "code", "source_file": "D:\\opencli\\clis\\douyin-videos\\_shared\\whisper-transcriber.js", "source_location": "L37"}, {"id": "whisper_transcriber_cleargpumemory", "label": "clearGPUMemory()", "file_type": "code", "source_file": "D:\\opencli\\clis\\douyin-videos\\_shared\\whisper-transcriber.js", "source_location": "L48"}, {"id": "whisper_transcriber_cleargpuandlog", "label": "clearGPUAndLog()", "file_type": "code", "source_file": "D:\\opencli\\clis\\douyin-videos\\_shared\\whisper-transcriber.js", "source_location": "L63"}, {"id": "whisper_transcriber_checkwhisperinstalled", "label": "checkWhisperInstalled()", "file_type": "code", "source_file": "D:\\opencli\\clis\\douyin-videos\\_shared\\whisper-transcriber.js", "source_location": "L73"}, {"id": "whisper_transcriber_transcribeaudio", "label": "transcribeAudio()", "file_type": "code", "source_file": "D:\\opencli\\clis\\douyin-videos\\_shared\\whisper-transcriber.js", "source_location": "L107"}, {"id": "whisper_transcriber_readtranscript", "label": "readTranscript()", "file_type": "code", "source_file": "D:\\opencli\\clis\\douyin-videos\\_shared\\whisper-transcriber.js", "source_location": "L266"}, {"id": "whisper_transcriber_transcribesinglesegment", "label": "transcribeSingleSegment()", "file_type": "code", "source_file": "D:\\opencli\\clis\\douyin-videos\\_shared\\whisper-transcriber.js", "source_location": "L275"}, {"id": "whisper_transcriber_findsegmenttranscript", "label": "findSegmentTranscript()", "file_type": "code", "source_file": "D:\\opencli\\clis\\douyin-videos\\_shared\\whisper-transcriber.js", "source_location": "L356"}, {"id": "whisper_transcriber_transcribeaudiowithsegments", "label": "transcribeAudioWithSegments()", "file_type": "code", "source_file": "D:\\opencli\\clis\\douyin-videos\\_shared\\whisper-transcriber.js", "source_location": "L373"}], "edges": [{"source": "d_opencli_clis_douyin_videos_shared_whisper_transcriber_js", "target": "fs", "relation": "imports_from", "confidence": "EXTRACTED", "source_file": "D:\\opencli\\clis\\douyin-videos\\_shared\\whisper-transcriber.js", "source_location": "L1", "weight": 1.0}, {"source": "d_opencli_clis_douyin_videos_shared_whisper_transcriber_js", "target": "path", "relation": "imports_from", "confidence": "EXTRACTED", "source_file": "D:\\opencli\\clis\\douyin-videos\\_shared\\whisper-transcriber.js", "source_location": "L2", "weight": 1.0}, {"source": "d_opencli_clis_douyin_videos_shared_whisper_transcriber_js", "target": "child_process", "relation": "imports_from", "confidence": "EXTRACTED", "source_file": "D:\\opencli\\clis\\douyin-videos\\_shared\\whisper-transcriber.js", "source_location": "L3", "weight": 1.0}, {"source": "d_opencli_clis_douyin_videos_shared_whisper_transcriber_js", "target": "d_opencli_clis_douyin_videos_shared_transcript_validator_ts", "relation": "imports_from", "confidence": "EXTRACTED", "source_file": "D:\\opencli\\clis\\douyin-videos\\_shared\\whisper-transcriber.js", "source_location": "L4", "weight": 1.0}, {"source": "d_opencli_clis_douyin_videos_shared_whisper_transcriber_js", "target": "d_opencli_clis_douyin_videos_shared_audio_splitter_ts", "relation": "imports_from", "confidence": "EXTRACTED", "source_file": "D:\\opencli\\clis\\douyin-videos\\_shared\\whisper-transcriber.js", "source_location": "L5", "weight": 1.0}, {"source": "d_opencli_clis_douyin_videos_shared_whisper_transcriber_js", "target": "whisper_transcriber_deduplicatetranscripttext", "relation": "contains", "confidence": "EXTRACTED", "source_file": "D:\\opencli\\clis\\douyin-videos\\_shared\\whisper-transcriber.js", "source_location": "L12", "weight": 1.0}, {"source": "d_opencli_clis_douyin_videos_shared_whisper_transcriber_js", "target": "whisper_transcriber_gettimeoutoptions", "relation": "contains", "confidence": "EXTRACTED", "source_file": "D:\\opencli\\clis\\douyin-videos\\_shared\\whisper-transcriber.js", "source_location": "L30", "weight": 1.0}, {"source": "d_opencli_clis_douyin_videos_shared_whisper_transcriber_js", "target": "whisper_transcriber_checkgpuavailable", "relation": "contains", "confidence": "EXTRACTED", "source_file": "D:\\opencli\\clis\\douyin-videos\\_shared\\whisper-transcriber.js", "source_location": "L37", "weight": 1.0}, {"source": "d_opencli_clis_douyin_videos_shared_whisper_transcriber_js", "target": "whisper_transcriber_cleargpumemory", "relation": "contains", "confidence": "EXTRACTED", "source_file": "D:\\opencli\\clis\\douyin-videos\\_shared\\whisper-transcriber.js", "source_location": "L48", "weight": 1.0}, {"source": "d_opencli_clis_douyin_videos_shared_whisper_transcriber_js", "target": "whisper_transcriber_cleargpuandlog", "relation": "contains", "confidence": "EXTRACTED", "source_file": "D:\\opencli\\clis\\douyin-videos\\_shared\\whisper-transcriber.js", "source_location": "L63", "weight": 1.0}, {"source": "d_opencli_clis_douyin_videos_shared_whisper_transcriber_js", "target": "whisper_transcriber_checkwhisperinstalled", "relation": "contains", "confidence": "EXTRACTED", "source_file": "D:\\opencli\\clis\\douyin-videos\\_shared\\whisper-transcriber.js", "source_location": "L73", "weight": 1.0}, {"source": "d_opencli_clis_douyin_videos_shared_whisper_transcriber_js", "target": "whisper_transcriber_transcribeaudio", "relation": "contains", "confidence": "EXTRACTED", "source_file": "D:\\opencli\\clis\\douyin-videos\\_shared\\whisper-transcriber.js", "source_location": "L107", "weight": 1.0}, {"source": "d_opencli_clis_douyin_videos_shared_whisper_transcriber_js", "target": "whisper_transcriber_readtranscript", "relation": "contains", "confidence": "EXTRACTED", "source_file": "D:\\opencli\\clis\\douyin-videos\\_shared\\whisper-transcriber.js", "source_location": "L266", "weight": 1.0}, {"source": "d_opencli_clis_douyin_videos_shared_whisper_transcriber_js", "target": "whisper_transcriber_transcribesinglesegment", "relation": "contains", "confidence": "EXTRACTED", "source_file": "D:\\opencli\\clis\\douyin-videos\\_shared\\whisper-transcriber.js", "source_location": "L275", "weight": 1.0}, {"source": "d_opencli_clis_douyin_videos_shared_whisper_transcriber_js", "target": "whisper_transcriber_findsegmenttranscript", "relation": "contains", "confidence": "EXTRACTED", "source_file": "D:\\opencli\\clis\\douyin-videos\\_shared\\whisper-transcriber.js", "source_location": "L356", "weight": 1.0}, {"source": "d_opencli_clis_douyin_videos_shared_whisper_transcriber_js", "target": "whisper_transcriber_transcribeaudiowithsegments", "relation": "contains", "confidence": "EXTRACTED", "source_file": "D:\\opencli\\clis\\douyin-videos\\_shared\\whisper-transcriber.js", "source_location": "L373", "weight": 1.0}, {"source": "whisper_transcriber_cleargpuandlog", "target": "whisper_transcriber_cleargpumemory", "relation": "calls", "confidence": "EXTRACTED", "source_file": "D:\\opencli\\clis\\douyin-videos\\_shared\\whisper-transcriber.js", "source_location": "L67", "weight": 1.0}, {"source": "whisper_transcriber_transcribeaudio", "target": "whisper_transcriber_gettimeoutoptions", "relation": "calls", "confidence": "EXTRACTED", "source_file": "D:\\opencli\\clis\\douyin-videos\\_shared\\whisper-transcriber.js", "source_location": "L120", "weight": 1.0}, {"source": "whisper_transcriber_transcribeaudio", "target": "whisper_transcriber_cleargpuandlog", "relation": "calls", "confidence": "EXTRACTED", "source_file": "D:\\opencli\\clis\\douyin-videos\\_shared\\whisper-transcriber.js", "source_location": "L139", "weight": 1.0}, {"source": "whisper_transcriber_transcribeaudio", "target": "whisper_transcriber_deduplicatetranscripttext", "relation": "calls", "confidence": "EXTRACTED", "source_file": "D:\\opencli\\clis\\douyin-videos\\_shared\\whisper-transcriber.js", "source_location": "L238", "weight": 1.0}, {"source": "whisper_transcriber_transcribesinglesegment", "target": "whisper_transcriber_gettimeoutoptions", "relation": "calls", "confidence": "EXTRACTED", "source_file": "D:\\opencli\\clis\\douyin-videos\\_shared\\whisper-transcriber.js", "source_location": "L277", "weight": 1.0}, {"source": "whisper_transcriber_transcribeaudiowithsegments", "target": "whisper_transcriber_transcribeaudio", "relation": "calls", "confidence": "EXTRACTED", "source_file": "D:\\opencli\\clis\\douyin-videos\\_shared\\whisper-transcriber.js", "source_location": "L415", "weight": 1.0}, {"source": "whisper_transcriber_transcribeaudiowithsegments", "target": "whisper_transcriber_findsegmenttranscript", "relation": "calls", "confidence": "EXTRACTED", "source_file": "D:\\opencli\\clis\\douyin-videos\\_shared\\whisper-transcriber.js", "source_location": "L441", "weight": 1.0}, {"source": "whisper_transcriber_transcribeaudiowithsegments", "target": "whisper_transcriber_transcribesinglesegment", "relation": "calls", "confidence": "EXTRACTED", "source_file": "D:\\opencli\\clis\\douyin-videos\\_shared\\whisper-transcriber.js", "source_location": "L462", "weight": 1.0}, {"source": "whisper_transcriber_transcribeaudiowithsegments", "target": "whisper_transcriber_deduplicatetranscripttext", "relation": "calls", "confidence": "EXTRACTED", "source_file": "D:\\opencli\\clis\\douyin-videos\\_shared\\whisper-transcriber.js", "source_location": "L510", "weight": 1.0}], "raw_calls": [{"caller_nid": "whisper_transcriber_deduplicatetranscripttext", "callee": "filter", "source_file": "D:\\opencli\\clis\\douyin-videos\\_shared\\whisper-transcriber.js", "source_location": "L13"}, {"caller_nid": "whisper_transcriber_deduplicatetranscripttext", "callee": "split", "source_file": "D:\\opencli\\clis\\douyin-videos\\_shared\\whisper-transcriber.js", "source_location": "L13"}, {"caller_nid": "whisper_transcriber_deduplicatetranscripttext", "callee": "join", "source_file": "D:\\opencli\\clis\\douyin-videos\\_shared\\whisper-transcriber.js", "source_location": "L19"}, {"caller_nid": "whisper_transcriber_gettimeoutoptions", "callee": "ceil", "source_file": "D:\\opencli\\clis\\douyin-videos\\_shared\\whisper-transcriber.js", "source_location": "L33"}, {"caller_nid": "whisper_transcriber_gettimeoutoptions", "callee": "max", "source_file": "D:\\opencli\\clis\\douyin-videos\\_shared\\whisper-transcriber.js", "source_location": "L34"}, {"caller_nid": "whisper_transcriber_checkgpuavailable", "callee": "execSync", "source_file": "D:\\opencli\\clis\\douyin-videos\\_shared\\whisper-transcriber.js", "source_location": "L39"}, {"caller_nid": "whisper_transcriber_checkgpuavailable", "callee": "includes", "source_file": "D:\\opencli\\clis\\douyin-videos\\_shared\\whisper-transcriber.js", "source_location": "L40"}, {"caller_nid": "whisper_transcriber_checkgpuavailable", "callee": "includes", "source_file": "D:\\opencli\\clis\\douyin-videos\\_shared\\whisper-transcriber.js", "source_location": "L40"}, {"caller_nid": "whisper_transcriber_cleargpumemory", "callee": "execSync", "source_file": "D:\\opencli\\clis\\douyin-videos\\_shared\\whisper-transcriber.js", "source_location": "L52"}, {"caller_nid": "whisper_transcriber_cleargpuandlog", "callee": "log", "source_file": "D:\\opencli\\clis\\douyin-videos\\_shared\\whisper-transcriber.js", "source_location": "L69"}, {"caller_nid": "whisper_transcriber_checkwhisperinstalled", "callee": "execSync", "source_file": "D:\\opencli\\clis\\douyin-videos\\_shared\\whisper-transcriber.js", "source_location": "L76"}, {"caller_nid": "whisper_transcriber_checkwhisperinstalled", "callee": "split", "source_file": "D:\\opencli\\clis\\douyin-videos\\_shared\\whisper-transcriber.js", "source_location": "L80"}, {"caller_nid": "whisper_transcriber_checkwhisperinstalled", "callee": "trim", "source_file": "D:\\opencli\\clis\\douyin-videos\\_shared\\whisper-transcriber.js", "source_location": "L80"}, {"caller_nid": "whisper_transcriber_checkwhisperinstalled", "callee": "execSync", "source_file": "D:\\opencli\\clis\\douyin-videos\\_shared\\whisper-transcriber.js", "source_location": "L83"}, {"caller_nid": "whisper_transcriber_checkwhisperinstalled", "callee": "execSync", "source_file": "D:\\opencli\\clis\\douyin-videos\\_shared\\whisper-transcriber.js", "source_location": "L92"}, {"caller_nid": "whisper_transcriber_transcribeaudio", "callee": "existsSync", "source_file": "D:\\opencli\\clis\\douyin-videos\\_shared\\whisper-transcriber.js", "source_location": "L115"}, {"caller_nid": "whisper_transcriber_transcribeaudio", "callee": "getAudioDuration", "source_file": "D:\\opencli\\clis\\douyin-videos\\_shared\\whisper-transcriber.js", "source_location": "L119"}, {"caller_nid": "whisper_transcriber_transcribeaudio", "callee": "basename", "source_file": "D:\\opencli\\clis\\douyin-videos\\_shared\\whisper-transcriber.js", "source_location": "L122"}, {"caller_nid": "whisper_transcriber_transcribeaudio", "callee": "extname", "source_file": "D:\\opencli\\clis\\douyin-videos\\_shared\\whisper-transcriber.js", "source_location": "L122"}, {"caller_nid": "whisper_transcriber_transcribeaudio", "callee": "join", "source_file": "D:\\opencli\\clis\\douyin-videos\\_shared\\whisper-transcriber.js", "source_location": "L123"}, {"caller_nid": "whisper_transcriber_transcribeaudio", "callee": "existsSync", "source_file": "D:\\opencli\\clis\\douyin-videos\\_shared\\whisper-transcriber.js", "source_location": "L125"}, {"caller_nid": "whisper_transcriber_transcribeaudio", "callee": "validateTranscript", "source_file": "D:\\opencli\\clis\\douyin-videos\\_shared\\whisper-transcriber.js", "source_location": "L126"}, {"caller_nid": "whisper_transcriber_transcribeaudio", "callee": "log", "source_file": "D:\\opencli\\clis\\douyin-videos\\_shared\\whisper-transcriber.js", "source_location": "L128"}, {"caller_nid": "whisper_transcriber_transcribeaudio", "callee": "unlinkSync", "source_file": "D:\\opencli\\clis\\douyin-videos\\_shared\\whisper-transcriber.js", "source_location": "L131"}, {"caller_nid": "whisper_transcriber_transcribeaudio", "callee": "existsSync", "source_file": "D:\\opencli\\clis\\douyin-videos\\_shared\\whisper-transcriber.js", "source_location": "L134"}, {"caller_nid": "whisper_transcriber_transcribeaudio", "callee": "mkdirSync", "source_file": "D:\\opencli\\clis\\douyin-videos\\_shared\\whisper-transcriber.js", "source_location": "L135"}, {"caller_nid": "whisper_transcriber_transcribeaudio", "callee": "log", "source_file": "D:\\opencli\\clis\\douyin-videos\\_shared\\whisper-transcriber.js", "source_location": "L142"}, {"caller_nid": "whisper_transcriber_transcribeaudio", "callee": "push", "source_file": "D:\\opencli\\clis\\douyin-videos\\_shared\\whisper-transcriber.js", "source_location": "L153"}, {"caller_nid": "whisper_transcriber_transcribeaudio", "callee": "join", "source_file": "D:\\opencli\\clis\\douyin-videos\\_shared\\whisper-transcriber.js", "source_location": "L218"}, {"caller_nid": "whisper_transcriber_transcribeaudio", "callee": "existsSync", "source_file": "D:\\opencli\\clis\\douyin-videos\\_shared\\whisper-transcriber.js", "source_location": "L219"}, {"caller_nid": "whisper_transcriber_transcribeaudio", "callee": "renameSync", "source_file": "D:\\opencli\\clis\\douyin-videos\\_shared\\whisper-transcriber.js", "source_location": "L221"}, {"caller_nid": "whisper_transcriber_transcribeaudio", "callee": "filter", "source_file": "D:\\opencli\\clis\\douyin-videos\\_shared\\whisper-transcriber.js", "source_location": "L224"}, {"caller_nid": "whisper_transcriber_transcribeaudio", "callee": "readdirSync", "source_file": "D:\\opencli\\clis\\douyin-videos\\_shared\\whisper-transcriber.js", "source_location": "L224"}, {"caller_nid": "whisper_transcriber_transcribeaudio", "callee": "join", "source_file": "D:\\opencli\\clis\\douyin-videos\\_shared\\whisper-transcriber.js", "source_location": "L228"}, {"caller_nid": "whisper_transcriber_transcribeaudio", "callee": "renameSync", "source_file": "D:\\opencli\\clis\\douyin-videos\\_shared\\whisper-transcriber.js", "source_location": "L229"}, {"caller_nid": "whisper_transcriber_transcribeaudio", "callee": "existsSync", "source_file": "D:\\opencli\\clis\\douyin-videos\\_shared\\whisper-transcriber.js", "source_location": "L233"}, {"caller_nid": "whisper_transcriber_transcribeaudio", "callee": "readFileSync", "source_file": "D:\\opencli\\clis\\douyin-videos\\_shared\\whisper-transcriber.js", "source_location": "L237"}, {"caller_nid": "whisper_transcriber_transcribeaudio", "callee": "writeFileSync", "source_file": "D:\\opencli\\clis\\douyin-videos\\_shared\\whisper-transcriber.js", "source_location": "L240"}, {"caller_nid": "whisper_transcriber_transcribeaudio", "callee": "log", "source_file": "D:\\opencli\\clis\\douyin-videos\\_shared\\whisper-transcriber.js", "source_location": "L241"}, {"caller_nid": "whisper_transcriber_transcribeaudio", "callee": "toFixed", "source_file": "D:\\opencli\\clis\\douyin-videos\\_shared\\whisper-transcriber.js", "source_location": "L241"}, {"caller_nid": "whisper_transcriber_transcribeaudio", "callee": "validateTranscript", "source_file": "D:\\opencli\\clis\\douyin-videos\\_shared\\whisper-transcriber.js", "source_location": "L244"}, {"caller_nid": "whisper_transcriber_transcribeaudio", "callee": "log", "source_file": "D:\\opencli\\clis\\douyin-videos\\_shared\\whisper-transcriber.js", "source_location": "L253"}, {"caller_nid": "whisper_transcriber_transcribeaudio", "callee": "filter", "source_file": "D:\\opencli\\clis\\douyin-videos\\_shared\\whisper-transcriber.js", "source_location": "L256"}, {"caller_nid": "whisper_transcriber_transcribeaudio", "callee": "readdirSync", "source_file": "D:\\opencli\\clis\\douyin-videos\\_shared\\whisper-transcriber.js", "source_location": "L256"}, {"caller_nid": "whisper_transcriber_transcribeaudio", "callee": "unlinkSync", "source_file": "D:\\opencli\\clis\\douyin-videos\\_shared\\whisper-transcriber.js", "source_location": "L259"}, {"caller_nid": "whisper_transcriber_transcribeaudio", "callee": "join", "source_file": "D:\\opencli\\clis\\douyin-videos\\_shared\\whisper-transcriber.js", "source_location": "L259"}, {"caller_nid": "whisper_transcriber_readtranscript", "callee": "existsSync", "source_file": "D:\\opencli\\clis\\douyin-videos\\_shared\\whisper-transcriber.js", "source_location": "L267"}, {"caller_nid": "whisper_transcriber_readtranscript", "callee": "readFileSync", "source_file": "D:\\opencli\\clis\\douyin-videos\\_shared\\whisper-transcriber.js", "source_location": "L271"}, {"caller_nid": "whisper_transcriber_readtranscript", "callee": "trim", "source_file": "D:\\opencli\\clis\\douyin-videos\\_shared\\whisper-transcriber.js", "source_location": "L272"}, {"caller_nid": "whisper_transcriber_transcribesinglesegment", "callee": "push", "source_file": "D:\\opencli\\clis\\douyin-videos\\_shared\\whisper-transcriber.js", "source_location": "L288"}, {"caller_nid": "whisper_transcriber_findsegmenttranscript", "callee": "padStart", "source_file": "D:\\opencli\\clis\\douyin-videos\\_shared\\whisper-transcriber.js", "source_location": "L358"}, {"caller_nid": "whisper_transcriber_findsegmenttranscript", "callee": "String", "source_file": "D:\\opencli\\clis\\douyin-videos\\_shared\\whisper-transcriber.js", "source_location": "L358"}, {"caller_nid": "whisper_transcriber_findsegmenttranscript", "callee": "basename", "source_file": "D:\\opencli\\clis\\douyin-videos\\_shared\\whisper-transcriber.js", "source_location": "L360"}, {"caller_nid": "whisper_transcriber_findsegmenttranscript", "callee": "padStart", "source_file": "D:\\opencli\\clis\\douyin-videos\\_shared\\whisper-transcriber.js", "source_location": "L360"}, {"caller_nid": "whisper_transcriber_findsegmenttranscript", "callee": "String", "source_file": "D:\\opencli\\clis\\douyin-videos\\_shared\\whisper-transcriber.js", "source_location": "L360"}, {"caller_nid": "whisper_transcriber_findsegmenttranscript", "callee": "join", "source_file": "D:\\opencli\\clis\\douyin-videos\\_shared\\whisper-transcriber.js", "source_location": "L364"}, {"caller_nid": "whisper_transcriber_findsegmenttranscript", "callee": "existsSync", "source_file": "D:\\opencli\\clis\\douyin-videos\\_shared\\whisper-transcriber.js", "source_location": "L365"}, {"caller_nid": "whisper_transcriber_transcribeaudiowithsegments", "callee": "existsSync", "source_file": "D:\\opencli\\clis\\douyin-videos\\_shared\\whisper-transcriber.js", "source_location": "L381"}, {"caller_nid": "whisper_transcriber_transcribeaudiowithsegments", "callee": "basename", "source_file": "D:\\opencli\\clis\\douyin-videos\\_shared\\whisper-transcriber.js", "source_location": "L385"}, {"caller_nid": "whisper_transcriber_transcribeaudiowithsegments", "callee": "extname", "source_file": "D:\\opencli\\clis\\douyin-videos\\_shared\\whisper-transcriber.js", "source_location": "L385"}, {"caller_nid": "whisper_transcriber_transcribeaudiowithsegments", "callee": "join", "source_file": "D:\\opencli\\clis\\douyin-videos\\_shared\\whisper-transcriber.js", "source_location": "L386"}, {"caller_nid": "whisper_transcriber_transcribeaudiowithsegments", "callee": "existsSync", "source_file": "D:\\opencli\\clis\\douyin-videos\\_shared\\whisper-transcriber.js", "source_location": "L388"}, {"caller_nid": "whisper_transcriber_transcribeaudiowithsegments", "callee": "validateTranscript", "source_file": "D:\\opencli\\clis\\douyin-videos\\_shared\\whisper-transcriber.js", "source_location": "L389"}, {"caller_nid": "whisper_transcriber_transcribeaudiowithsegments", "callee": "log", "source_file": "D:\\opencli\\clis\\douyin-videos\\_shared\\whisper-transcriber.js", "source_location": "L391"}, {"caller_nid": "whisper_transcriber_transcribeaudiowithsegments", "callee": "unlinkSync", "source_file": "D:\\opencli\\clis\\douyin-videos\\_shared\\whisper-transcriber.js", "source_location": "L394"}, {"caller_nid": "whisper_transcriber_transcribeaudiowithsegments", "callee": "existsSync", "source_file": "D:\\opencli\\clis\\douyin-videos\\_shared\\whisper-transcriber.js", "source_location": "L397"}, {"caller_nid": "whisper_transcriber_transcribeaudiowithsegments", "callee": "mkdirSync", "source_file": "D:\\opencli\\clis\\douyin-videos\\_shared\\whisper-transcriber.js", "source_location": "L398"}, {"caller_nid": "whisper_transcriber_transcribeaudiowithsegments", "callee": "getAudioDuration", "source_file": "D:\\opencli\\clis\\douyin-videos\\_shared\\whisper-transcriber.js", "source_location": "L401"}, {"caller_nid": "whisper_transcriber_transcribeaudiowithsegments", "callee": "log", "source_file": "D:\\opencli\\clis\\douyin-videos\\_shared\\whisper-transcriber.js", "source_location": "L405"}, {"caller_nid": "whisper_transcriber_transcribeaudiowithsegments", "callee": "toFixed", "source_file": "D:\\opencli\\clis\\douyin-videos\\_shared\\whisper-transcriber.js", "source_location": "L405"}, {"caller_nid": "whisper_transcriber_transcribeaudiowithsegments", "callee": "toFixed", "source_file": "D:\\opencli\\clis\\douyin-videos\\_shared\\whisper-transcriber.js", "source_location": "L408"}, {"caller_nid": "whisper_transcriber_transcribeaudiowithsegments", "callee": "isLongAudio", "source_file": "D:\\opencli\\clis\\douyin-videos\\_shared\\whisper-transcriber.js", "source_location": "L413"}, {"caller_nid": "whisper_transcriber_transcribeaudiowithsegments", "callee": "log", "source_file": "D:\\opencli\\clis\\douyin-videos\\_shared\\whisper-transcriber.js", "source_location": "L414"}, {"caller_nid": "whisper_transcriber_transcribeaudiowithsegments", "callee": "toFixed", "source_file": "D:\\opencli\\clis\\douyin-videos\\_shared\\whisper-transcriber.js", "source_location": "L414"}, {"caller_nid": "whisper_transcriber_transcribeaudiowithsegments", "callee": "log", "source_file": "D:\\opencli\\clis\\douyin-videos\\_shared\\whisper-transcriber.js", "source_location": "L418"}, {"caller_nid": "whisper_transcriber_transcribeaudiowithsegments", "callee": "toFixed", "source_file": "D:\\opencli\\clis\\douyin-videos\\_shared\\whisper-transcriber.js", "source_location": "L418"}, {"caller_nid": "whisper_transcriber_transcribeaudiowithsegments", "callee": "join", "source_file": "D:\\opencli\\clis\\douyin-videos\\_shared\\whisper-transcriber.js", "source_location": "L420"}, {"caller_nid": "whisper_transcriber_transcribeaudiowithsegments", "callee": "splitAudio", "source_file": "D:\\opencli\\clis\\douyin-videos\\_shared\\whisper-transcriber.js", "source_location": "L421"}, {"caller_nid": "whisper_transcriber_transcribeaudiowithsegments", "callee": "log", "source_file": "D:\\opencli\\clis\\douyin-videos\\_shared\\whisper-transcriber.js", "source_location": "L424"}, {"caller_nid": "whisper_transcriber_transcribeaudiowithsegments", "callee": "log", "source_file": "D:\\opencli\\clis\\douyin-videos\\_shared\\whisper-transcriber.js", "source_location": "L432"}, {"caller_nid": "whisper_transcriber_transcribeaudiowithsegments", "callee": "log", "source_file": "D:\\opencli\\clis\\douyin-videos\\_shared\\whisper-transcriber.js", "source_location": "L439"}, {"caller_nid": "whisper_transcriber_transcribeaudiowithsegments", "callee": "toFixed", "source_file": "D:\\opencli\\clis\\douyin-videos\\_shared\\whisper-transcriber.js", "source_location": "L439"}, {"caller_nid": "whisper_transcriber_transcribeaudiowithsegments", "callee": "existsSync", "source_file": "D:\\opencli\\clis\\douyin-videos\\_shared\\whisper-transcriber.js", "source_location": "L443"}, {"caller_nid": "whisper_transcriber_transcribeaudiowithsegments", "callee": "trim", "source_file": "D:\\opencli\\clis\\douyin-videos\\_shared\\whisper-transcriber.js", "source_location": "L444"}, {"caller_nid": "whisper_transcriber_transcribeaudiowithsegments", "callee": "readFileSync", "source_file": "D:\\opencli\\clis\\douyin-videos\\_shared\\whisper-transcriber.js", "source_location": "L444"}, {"caller_nid": "whisper_transcriber_transcribeaudiowithsegments", "callee": "log", "source_file": "D:\\opencli\\clis\\douyin-videos\\_shared\\whisper-transcriber.js", "source_location": "L447"}, {"caller_nid": "whisper_transcriber_transcribeaudiowithsegments", "callee": "push", "source_file": "D:\\opencli\\clis\\douyin-videos\\_shared\\whisper-transcriber.js", "source_location": "L448"}, {"caller_nid": "whisper_transcriber_transcribeaudiowithsegments", "callee": "existsSync", "source_file": "D:\\opencli\\clis\\douyin-videos\\_shared\\whisper-transcriber.js", "source_location": "L472"}, {"caller_nid": "whisper_transcriber_transcribeaudiowithsegments", "callee": "trim", "source_file": "D:\\opencli\\clis\\douyin-videos\\_shared\\whisper-transcriber.js", "source_location": "L473"}, {"caller_nid": "whisper_transcriber_transcribeaudiowithsegments", "callee": "readFileSync", "source_file": "D:\\opencli\\clis\\douyin-videos\\_shared\\whisper-transcriber.js", "source_location": "L473"}, {"caller_nid": "whisper_transcriber_transcribeaudiowithsegments", "callee": "push", "source_file": "D:\\opencli\\clis\\douyin-videos\\_shared\\whisper-transcriber.js", "source_location": "L476"}, {"caller_nid": "whisper_transcriber_transcribeaudiowithsegments", "callee": "log", "source_file": "D:\\opencli\\clis\\douyin-videos\\_shared\\whisper-transcriber.js", "source_location": "L484"}, {"caller_nid": "whisper_transcriber_transcribeaudiowithsegments", "callee": "log", "source_file": "D:\\opencli\\clis\\douyin-videos\\_shared\\whisper-transcriber.js", "source_location": "L486"}, {"caller_nid": "whisper_transcriber_transcribeaudiowithsegments", "callee": "log", "source_file": "D:\\opencli\\clis\\douyin-videos\\_shared\\whisper-transcriber.js", "source_location": "L489"}, {"caller_nid": "whisper_transcriber_transcribeaudiowithsegments", "callee": "log", "source_file": "D:\\opencli\\clis\\douyin-videos\\_shared\\whisper-transcriber.js", "source_location": "L492"}, {"caller_nid": "whisper_transcriber_transcribeaudiowithsegments", "callee": "cleanupSegments", "source_file": "D:\\opencli\\clis\\douyin-videos\\_shared\\whisper-transcriber.js", "source_location": "L499"}, {"caller_nid": "whisper_transcriber_transcribeaudiowithsegments", "callee": "sort", "source_file": "D:\\opencli\\clis\\douyin-videos\\_shared\\whisper-transcriber.js", "source_location": "L503"}, {"caller_nid": "whisper_transcriber_transcribeaudiowithsegments", "callee": "trim", "source_file": "D:\\opencli\\clis\\douyin-videos\\_shared\\whisper-transcriber.js", "source_location": "L505"}, {"caller_nid": "whisper_transcriber_transcribeaudiowithsegments", "callee": "join", "source_file": "D:\\opencli\\clis\\douyin-videos\\_shared\\whisper-transcriber.js", "source_location": "L505"}, {"caller_nid": "whisper_transcriber_transcribeaudiowithsegments", "callee": "map", "source_file": "D:\\opencli\\clis\\douyin-videos\\_shared\\whisper-transcriber.js", "source_location": "L505"}, {"caller_nid": "whisper_transcriber_transcribeaudiowithsegments", "callee": "writeFileSync", "source_file": "D:\\opencli\\clis\\douyin-videos\\_shared\\whisper-transcriber.js", "source_location": "L514"}, {"caller_nid": "whisper_transcriber_transcribeaudiowithsegments", "callee": "validateTranscript", "source_file": "D:\\opencli\\clis\\douyin-videos\\_shared\\whisper-transcriber.js", "source_location": "L516"}, {"caller_nid": "whisper_transcriber_transcribeaudiowithsegments", "callee": "log", "source_file": "D:\\opencli\\clis\\douyin-videos\\_shared\\whisper-transcriber.js", "source_location": "L518"}, {"caller_nid": "whisper_transcriber_transcribeaudiowithsegments", "callee": "log", "source_file": "D:\\opencli\\clis\\douyin-videos\\_shared\\whisper-transcriber.js", "source_location": "L519"}, {"caller_nid": "whisper_transcriber_transcribeaudiowithsegments", "callee": "log", "source_file": "D:\\opencli\\clis\\douyin-videos\\_shared\\whisper-transcriber.js", "source_location": "L520"}, {"caller_nid": "whisper_transcriber_transcribeaudiowithsegments", "callee": "log", "source_file": "D:\\opencli\\clis\\douyin-videos\\_shared\\whisper-transcriber.js", "source_location": "L521"}, {"caller_nid": "whisper_transcriber_transcribeaudiowithsegments", "callee": "log", "source_file": "D:\\opencli\\clis\\douyin-videos\\_shared\\whisper-transcriber.js", "source_location": "L523"}, {"caller_nid": "whisper_transcriber_transcribeaudiowithsegments", "callee": "toFixed", "source_file": "D:\\opencli\\clis\\douyin-videos\\_shared\\whisper-transcriber.js", "source_location": "L523"}, {"caller_nid": "whisper_transcriber_transcribeaudiowithsegments", "callee": "cleanupSegments", "source_file": "D:\\opencli\\clis\\douyin-videos\\_shared\\whisper-transcriber.js", "source_location": "L526"}, {"caller_nid": "whisper_transcriber_transcribeaudiowithsegments", "callee": "log", "source_file": "D:\\opencli\\clis\\douyin-videos\\_shared\\whisper-transcriber.js", "source_location": "L528"}, {"caller_nid": "whisper_transcriber_transcribeaudiowithsegments", "callee": "log", "source_file": "D:\\opencli\\clis\\douyin-videos\\_shared\\whisper-transcriber.js", "source_location": "L532"}]}