{"nodes": [{"id": "d_opencli_src_analysis_ts", "label": "analysis.ts", "file_type": "code", "source_file": "D:\\opencli\\src\\analysis.ts", "source_location": "L1"}, {"id": "analysis_urltopattern", "label": "urlToPattern()", "file_type": "code", "source_file": "D:\\opencli\\src\\analysis.ts", "source_location": "L24"}, {"id": "analysis_findarraypath", "label": "findArrayPath()", "file_type": "code", "source_file": "D:\\opencli\\src\\analysis.ts", "source_location": "L45"}, {"id": "analysis_flattenfields", "label": "flattenFields()", "file_type": "code", "source_file": "D:\\opencli\\src\\analysis.ts", "source_location": "L68"}, {"id": "analysis_detectfieldroles", "label": "detectFieldRoles()", "file_type": "code", "source_file": "D:\\opencli\\src\\analysis.ts", "source_location": "L82"}, {"id": "analysis_infercapabilityname", "label": "inferCapabilityName()", "file_type": "code", "source_file": "D:\\opencli\\src\\analysis.ts", "source_location": "L98"}, {"id": "analysis_inferstrategy", "label": "inferStrategy()", "file_type": "code", "source_file": "D:\\opencli\\src\\analysis.ts", "source_location": "L120"}, {"id": "analysis_detectauthfromheaders", "label": "detectAuthFromHeaders()", "file_type": "code", "source_file": "D:\\opencli\\src\\analysis.ts", "source_location": "L129"}, {"id": "analysis_detectauthfromcontent", "label": "detectAuthFromContent()", "file_type": "code", "source_file": "D:\\opencli\\src\\analysis.ts", "source_location": "L140"}, {"id": "analysis_isnoiseurl", "label": "isNoiseUrl()", "file_type": "code", "source_file": "D:\\opencli\\src\\analysis.ts", "source_location": "L158"}, {"id": "analysis_classifyqueryparams", "label": "classifyQueryParams()", "file_type": "code", "source_file": "D:\\opencli\\src\\analysis.ts", "source_location": "L165"}], "edges": [{"source": "d_opencli_src_analysis_ts", "target": "d_opencli_src_constants_ts", "relation": "imports_from", "confidence": "EXTRACTED", "source_file": "D:\\opencli\\src\\analysis.ts", "source_location": "L13", "weight": 1.0}, {"source": "d_opencli_src_analysis_ts", "target": "analysis_urltopattern", "relation": "contains", "confidence": "EXTRACTED", "source_file": "D:\\opencli\\src\\analysis.ts", "source_location": "L24", "weight": 1.0}, {"source": "d_opencli_src_analysis_ts", "target": "analysis_findarraypath", "relation": "contains", "confidence": "EXTRACTED", "source_file": "D:\\opencli\\src\\analysis.ts", "source_location": "L45", "weight": 1.0}, {"source": "d_opencli_src_analysis_ts", "target": "analysis_flattenfields", "relation": "contains", "confidence": "EXTRACTED", "source_file": "D:\\opencli\\src\\analysis.ts", "source_location": "L68", "weight": 1.0}, {"source": "d_opencli_src_analysis_ts", "target": "analysis_detectfieldroles", "relation": "contains", "confidence": "EXTRACTED", "source_file": "D:\\opencli\\src\\analysis.ts", "source_location": "L82", "weight": 1.0}, {"source": "d_opencli_src_analysis_ts", "target": "analysis_infercapabilityname", "relation": "contains", "confidence": "EXTRACTED", "source_file": "D:\\opencli\\src\\analysis.ts", "source_location": "L98", "weight": 1.0}, {"source": "d_opencli_src_analysis_ts", "target": "analysis_inferstrategy", "relation": "contains", "confidence": "EXTRACTED", "source_file": "D:\\opencli\\src\\analysis.ts", "source_location": "L120", "weight": 1.0}, {"source": "d_opencli_src_analysis_ts", "target": "analysis_detectauthfromheaders", "relation": "contains", "confidence": "EXTRACTED", "source_file": "D:\\opencli\\src\\analysis.ts", "source_location": "L129", "weight": 1.0}, {"source": "d_opencli_src_analysis_ts", "target": "analysis_detectauthfromcontent", "relation": "contains", "confidence": "EXTRACTED", "source_file": "D:\\opencli\\src\\analysis.ts", "source_location": "L140", "weight": 1.0}, {"source": "d_opencli_src_analysis_ts", "target": "analysis_isnoiseurl", "relation": "contains", "confidence": "EXTRACTED", "source_file": "D:\\opencli\\src\\analysis.ts", "source_location": "L158", "weight": 1.0}, {"source": "d_opencli_src_analysis_ts", "target": "analysis_classifyqueryparams", "relation": "contains", "confidence": "EXTRACTED", "source_file": "D:\\opencli\\src\\analysis.ts", "source_location": "L165", "weight": 1.0}], "raw_calls": [{"caller_nid": "analysis_urltopattern", "callee": "replace", "source_file": "D:\\opencli\\src\\analysis.ts", "source_location": "L27"}, {"caller_nid": "analysis_urltopattern", "callee": "replace", "source_file": "D:\\opencli\\src\\analysis.ts", "source_location": "L27"}, {"caller_nid": "analysis_urltopattern", "callee": "replace", "source_file": "D:\\opencli\\src\\analysis.ts", "source_location": "L27"}, {"caller_nid": "analysis_urltopattern", "callee": "forEach", "source_file": "D:\\opencli\\src\\analysis.ts", "source_location": "L32"}, {"caller_nid": "analysis_urltopattern", "callee": "join", "source_file": "D:\\opencli\\src\\analysis.ts", "source_location": "L33"}, {"caller_nid": "analysis_urltopattern", "callee": "map", "source_file": "D:\\opencli\\src\\analysis.ts", "source_location": "L33"}, {"caller_nid": "analysis_urltopattern", "callee": "sort", "source_file": "D:\\opencli\\src\\analysis.ts", "source_location": "L33"}, {"caller_nid": "analysis_findarraypath", "callee": "isArray", "source_file": "D:\\opencli\\src\\analysis.ts", "source_location": "L47"}, {"caller_nid": "analysis_findarraypath", "callee": "some", "source_file": "D:\\opencli\\src\\analysis.ts", "source_location": "L48"}, {"caller_nid": "analysis_findarraypath", "callee": "entries", "source_file": "D:\\opencli\\src\\analysis.ts", "source_location": "L54"}, {"caller_nid": "analysis_flattenfields", "callee": "keys", "source_file": "D:\\opencli\\src\\analysis.ts", "source_location": "L72"}, {"caller_nid": "analysis_flattenfields", "callee": "push", "source_file": "D:\\opencli\\src\\analysis.ts", "source_location": "L74"}, {"caller_nid": "analysis_flattenfields", "callee": "isArray", "source_file": "D:\\opencli\\src\\analysis.ts", "source_location": "L76"}, {"caller_nid": "analysis_flattenfields", "callee": "push", "source_file": "D:\\opencli\\src\\analysis.ts", "source_location": "L76"}, {"caller_nid": "analysis_detectfieldroles", "callee": "entries", "source_file": "D:\\opencli\\src\\analysis.ts", "source_location": "L84"}, {"caller_nid": "analysis_detectfieldroles", "callee": "includes", "source_file": "D:\\opencli\\src\\analysis.ts", "source_location": "L86"}, {"caller_nid": "analysis_detectfieldroles", "callee": "toLowerCase", "source_file": "D:\\opencli\\src\\analysis.ts", "source_location": "L86"}, {"caller_nid": "analysis_detectfieldroles", "callee": "pop", "source_file": "D:\\opencli\\src\\analysis.ts", "source_location": "L86"}, {"caller_nid": "analysis_detectfieldroles", "callee": "split", "source_file": "D:\\opencli\\src\\analysis.ts", "source_location": "L86"}, {"caller_nid": "analysis_infercapabilityname", "callee": "toLowerCase", "source_file": "D:\\opencli\\src\\analysis.ts", "source_location": "L100"}, {"caller_nid": "analysis_infercapabilityname", "callee": "includes", "source_file": "D:\\opencli\\src\\analysis.ts", "source_location": "L101"}, {"caller_nid": "analysis_infercapabilityname", "callee": "includes", "source_file": "D:\\opencli\\src\\analysis.ts", "source_location": "L101"}, {"caller_nid": "analysis_infercapabilityname", "callee": "includes", "source_file": "D:\\opencli\\src\\analysis.ts", "source_location": "L101"}, {"caller_nid": "analysis_infercapabilityname", "callee": "includes", "source_file": "D:\\opencli\\src\\analysis.ts", "source_location": "L101"}, {"caller_nid": "analysis_infercapabilityname", "callee": "includes", "source_file": "D:\\opencli\\src\\analysis.ts", "source_location": "L102"}, {"caller_nid": "analysis_infercapabilityname", "callee": "includes", "source_file": "D:\\opencli\\src\\analysis.ts", "source_location": "L103"}, {"caller_nid": "analysis_infercapabilityname", "callee": "includes", "source_file": "D:\\opencli\\src\\analysis.ts", "source_location": "L103"}, {"caller_nid": "analysis_infercapabilityname", "callee": "includes", "source_file": "D:\\opencli\\src\\analysis.ts", "source_location": "L103"}, {"caller_nid": "analysis_infercapabilityname", "callee": "includes", "source_file": "D:\\opencli\\src\\analysis.ts", "source_location": "L104"}, {"caller_nid": "analysis_infercapabilityname", "callee": "includes", "source_file": "D:\\opencli\\src\\analysis.ts", "source_location": "L104"}, {"caller_nid": "analysis_infercapabilityname", "callee": "includes", "source_file": "D:\\opencli\\src\\analysis.ts", "source_location": "L105"}, {"caller_nid": "analysis_infercapabilityname", "callee": "includes", "source_file": "D:\\opencli\\src\\analysis.ts", "source_location": "L106"}, {"caller_nid": "analysis_infercapabilityname", "callee": "includes", "source_file": "D:\\opencli\\src\\analysis.ts", "source_location": "L106"}, {"caller_nid": "analysis_infercapabilityname", "callee": "includes", "source_file": "D:\\opencli\\src\\analysis.ts", "source_location": "L106"}, {"caller_nid": "analysis_infercapabilityname", "callee": "includes", "source_file": "D:\\opencli\\src\\analysis.ts", "source_location": "L107"}, {"caller_nid": "analysis_infercapabilityname", "callee": "includes", "source_file": "D:\\opencli\\src\\analysis.ts", "source_location": "L107"}, {"caller_nid": "analysis_infercapabilityname", "callee": "includes", "source_file": "D:\\opencli\\src\\analysis.ts", "source_location": "L107"}, {"caller_nid": "analysis_infercapabilityname", "callee": "filter", "source_file": "D:\\opencli\\src\\analysis.ts", "source_location": "L109"}, {"caller_nid": "analysis_infercapabilityname", "callee": "split", "source_file": "D:\\opencli\\src\\analysis.ts", "source_location": "L109"}, {"caller_nid": "analysis_infercapabilityname", "callee": "toLowerCase", "source_file": "D:\\opencli\\src\\analysis.ts", "source_location": "L112"}, {"caller_nid": "analysis_infercapabilityname", "callee": "replace", "source_file": "D:\\opencli\\src\\analysis.ts", "source_location": "L112"}, {"caller_nid": "analysis_inferstrategy", "callee": "includes", "source_file": "D:\\opencli\\src\\analysis.ts", "source_location": "L121"}, {"caller_nid": "analysis_inferstrategy", "callee": "includes", "source_file": "D:\\opencli\\src\\analysis.ts", "source_location": "L122"}, {"caller_nid": "analysis_inferstrategy", "callee": "includes", "source_file": "D:\\opencli\\src\\analysis.ts", "source_location": "L122"}, {"caller_nid": "analysis_detectauthfromheaders", "callee": "map", "source_file": "D:\\opencli\\src\\analysis.ts", "source_location": "L132"}, {"caller_nid": "analysis_detectauthfromheaders", "callee": "keys", "source_file": "D:\\opencli\\src\\analysis.ts", "source_location": "L132"}, {"caller_nid": "analysis_detectauthfromheaders", "callee": "some", "source_file": "D:\\opencli\\src\\analysis.ts", "source_location": "L133"}, {"caller_nid": "analysis_detectauthfromheaders", "callee": "push", "source_file": "D:\\opencli\\src\\analysis.ts", "source_location": "L133"}, {"caller_nid": "analysis_detectauthfromheaders", "callee": "some", "source_file": "D:\\opencli\\src\\analysis.ts", "source_location": "L134"}, {"caller_nid": "analysis_detectauthfromheaders", "callee": "push", "source_file": "D:\\opencli\\src\\analysis.ts", "source_location": "L134"}, {"caller_nid": "analysis_detectauthfromheaders", "callee": "some", "source_file": "D:\\opencli\\src\\analysis.ts", "source_location": "L135"}, {"caller_nid": "analysis_detectauthfromheaders", "callee": "push", "source_file": "D:\\opencli\\src\\analysis.ts", "source_location": "L135"}, {"caller_nid": "analysis_detectauthfromcontent", "callee": "map", "source_file": "D:\\opencli\\src\\analysis.ts", "source_location": "L143"}, {"caller_nid": "analysis_detectauthfromcontent", "callee": "keys", "source_file": "D:\\opencli\\src\\analysis.ts", "source_location": "L143"}, {"caller_nid": "analysis_detectauthfromcontent", "callee": "some", "source_file": "D:\\opencli\\src\\analysis.ts", "source_location": "L144"}, {"caller_nid": "analysis_detectauthfromcontent", "callee": "push", "source_file": "D:\\opencli\\src\\analysis.ts", "source_location": "L145"}, {"caller_nid": "analysis_detectauthfromcontent", "callee": "includes", "source_file": "D:\\opencli\\src\\analysis.ts", "source_location": "L148"}, {"caller_nid": "analysis_detectauthfromcontent", "callee": "includes", "source_file": "D:\\opencli\\src\\analysis.ts", "source_location": "L148"}, {"caller_nid": "analysis_detectauthfromcontent", "callee": "push", "source_file": "D:\\opencli\\src\\analysis.ts", "source_location": "L148"}, {"caller_nid": "analysis_detectauthfromcontent", "callee": "includes", "source_file": "D:\\opencli\\src\\analysis.ts", "source_location": "L149"}, {"caller_nid": "analysis_detectauthfromcontent", "callee": "includes", "source_file": "D:\\opencli\\src\\analysis.ts", "source_location": "L149"}, {"caller_nid": "analysis_detectauthfromcontent", "callee": "push", "source_file": "D:\\opencli\\src\\analysis.ts", "source_location": "L149"}, {"caller_nid": "analysis_isnoiseurl", "callee": "test", "source_file": "D:\\opencli\\src\\analysis.ts", "source_location": "L159"}, {"caller_nid": "analysis_classifyqueryparams", "callee": "forEach", "source_file": "D:\\opencli\\src\\analysis.ts", "source_location": "L172"}, {"caller_nid": "analysis_classifyqueryparams", "callee": "some", "source_file": "D:\\opencli\\src\\analysis.ts", "source_location": "L175"}, {"caller_nid": "analysis_classifyqueryparams", "callee": "some", "source_file": "D:\\opencli\\src\\analysis.ts", "source_location": "L176"}, {"caller_nid": "analysis_classifyqueryparams", "callee": "some", "source_file": "D:\\opencli\\src\\analysis.ts", "source_location": "L177"}]}